{"aleppo":{"f":"\u0430\u043b\u0435\u043f\u043f\u043e","r":"aleppo","s":1.0},"app":{"f":"\u0430\u043f\u043f","r":"app","s":1.0},"arkhangelsk":{"f":"\u0430\u0440\u0445\u0430\u043d\u0433\u0435\u043b\u044c\u0441\u043a","r":"arkhangelsk","s":1.0},"banana":{"f":"\u0431\u0430\u043d\u0430\u043d\u0430","r":"banana","s":1.0},"belgorod":{"f":"\u0431\u0435\u043b\u0433\u043e\u0440\u043e\u0434","r":"belgorod","s":1.0},"benin":{"f":"\u0431\u0435\u043d\u0438\u043d","r":"benin","s":1.0},"bikini":{"f":"\u0431\u0438\u043a\u0438\u043d\u0438","r":"bikini","s":1.0},"element":{"f":"\u044d\u043b\u0435\u043c\u0435\u043d\u0442","r":"element","s":1.0},"fermion":{"f":"\u0444\u0435\u0440\u043c\u0438\u043e\u043d","r":"fermion","s":1.0},"gagarin":{"f":"\u0433\u0430\u0433\u0430\u0440\u0438\u043d","r":"gagarin","s":1.0},"generator":{"f":"\u0433\u0435\u043d\u0435\u0440\u0430\u0442\u043e\u0440","r":"generator","s":1.0},"german":{"f":"\u0433\u0435\u0440\u043c\u0430\u043d","r":"german","s":1.0},"gibraltar":{"f":"\u0433\u0438\u0431\u0440\u0430\u043b\u0442\u0430\u0440","r":"gibraltar","s":1.0},"integral":{"f":"\u0438\u043d\u0442\u0435\u0433\u0440\u0430\u043b","r":"integral","s":1.0},"islam":{"f":"\u0438\u0441\u043b\u0430\u043c","r":"islam","s":1.0},"jilin":{"f":"\u1835\u1822\u182f\u1822\u1828","r":"jilin","s":1.0},"kosovo":{"f":"\u043a\u043e\u0441\u043e\u0432\u043e","r":"kosovo","s":1.0},"kostroma":{"f":"\u043a\u043e\u0441\u0442\u0440\u043e\u043c\u0430","r":"kostroma","s":1.0},"krasnodar":{"f":"\u043a\u0440\u0430\u0441\u043d\u043e\u0434\u0430\u0440","r":"krasnodar","s":1.0},"kursk":{"f":"\u043a\u0443\u0440\u0441\u043a","r":"kursk","s":1.0},"leningrad":{"f":"\u043b\u0435\u043d\u0438\u043d\u0433\u0440\u0430\u0434","r":"leningrad","s":1.0},"london":{"f":"\u043b\u043e\u043d\u0434\u043e\u043d","r":"london","s":1.0},"mango":{"f":"\u043c\u0430\u043d\u0433\u043e","r":"mango","s":1.0},"noyan":{"f":"\u1828\u1823\u1836\u1820\u1828","r":"noyan","s":1.0},"paris":{"f":"\u043f\u0430\u0440\u0438\u0441","r":"paris","s":1.0},"park":{"f":"\u043f\u0430\u0440\u043a","r":"park","s":1.0},"perestroika":{"f":"\u043f\u0435\u0440\u0435\u0441\u0442\u0440\u043e\u0439\u043a\u0430","r":"perestroika","s":1.0},"perm":{"f":"\u043f\u0435\u0440\u043c\u044c","r":"perm","s":1.0},"program":{"f":"\u043f\u0440\u043e\u0433\u0440\u0430\u043c","r":"program","s":1.0},"putin":{"f":"\u043f\u0443\u0442\u0438\u043d","r":"putin","s":1.0},"radar":{"f":"\u0440\u0430\u0434\u0430\u0440","r":"radar","s":1.0},"sakhalin":{"f":"\u0441\u0430\u0445\u0430\u043b\u0438\u043d","r":"sakhalin","s":1.0},"sudan":{"f":"\u0441\u0443\u0434\u0430\u043d","r":"sudan","s":1.0},"ton":{"f":"\u1832\u180b\u1823\u1828","r":"ton","s":1.0},"tunis":{"f":"\u0442\u0443\u043d\u0438\u0441","r":"tunis","s":1.0},"virus":{"f":"\u0432\u0438\u0440\u0443\u0441","r":"virus","s":1.0},"zagreb":{"f":"\u0437\u0430\u0433\u0440\u0435\u0431","r":"zagreb","s":1.0},"palestine":{"f":"\u043f\u0430\u043b\u0435\u0441\u0442\u0438\u043d","r":"palestin","s":0.9359},"aerodrome":{"f":"\u0430\u044d\u0440\u043e\u0434\u0440\u043e\u043c","r":"aerodrom","s":0.9341},"lesbian":{"f":"\u043b\u0435\u0441\u0431\u0438\u044f\u043d","r":"lesbiian","s":0.9143},"metal":{"f":"\u043c\u0435\u0442\u0430\u043b\u043b","r":"metall","s":0.9008},"samara":{"f":"\u0441\u0430\u043c\u0430\u0440","r":"samar","s":0.9008},"eritrea":{"f":"\u044d\u0440\u0438\u0442\u0440\u0435\u0439","r":"eritrei","s":0.8976},"sarkozy":{"f":"\u0441\u0430\u0440\u043a\u043e\u0437\u0438","r":"sarkozi","s":0.8976},"tatar":{"f":"\u0442\u0430\u0442\u0430\u0430\u0440","r":"tataar","s":0.8783},"ireland":{"f":"\u0438\u0440\u043b\u0430\u043d\u0434","r":"irland","s":0.8619},"pyramid":{"f":"\u043f\u0438\u0440\u0430\u043c\u0438\u0434","r":"piramid","s":0.8571},"vatican":{"f":"\u0432\u0430\u0442\u0438\u043a\u0430\u043d","r":"vatikan","s":0.8554},"altay":{"f":"\u0430\u043b\u0442\u0430\u0439","r":"altai","s":0.855},"salad":{"f":"\u0441\u0430\u043b\u0430\u0442","r":"salat","s":0.855},"mongolia":{"f":"\u043c\u043e\u043d\u0433\u043e\u043b","r":"mongol","s":0.8548},"kopek":{"f":"\u043a\u043e\u043f\u0435\u0439\u043a","r":"kopeik","s":0.8533},"zelenskyy":{"f":"\u0437\u0435\u043b\u0435\u043d\u0441\u043a\u0438\u0439","r":"zelenskii","s":0.8489},"autism":{"f":"\u0430\u0443\u0442\u0438\u0437\u043c","r":"autizm","s":0.8429},"mile":{"f":"\u043c\u0438\u043b\u044c","r":"mil","s":0.8396},"armenia":{"f":"\u0430\u0440\u043c\u0435\u043d","r":"armen","s":0.8324},"britain":{"f":"\u0431\u0440\u0438\u0442\u0430\u043d\u0438","r":"britani","s":0.8286},"vancouver":{"f":"\u0432\u0430\u043d\u043a\u0443\u0432\u0435\u0440","r":"vankuver","s":0.8225},"vientiane":{"f":"\u0432\u044c\u0435\u043d\u0442\u044c\u044f\u043d","r":"ventian","s":0.8147},"matter":{"f":"\u043c\u0430\u0442\u0435\u0440\u0438","r":"materi","s":0.8139},"communism":{"f":"\u183a\u1823\u182e\u182e\u1826\u180b\u1828\u1822\u1830\u182e","r":"kommunism","s":0.8134},"etymology":{"f":"\u044d\u0442\u0438\u043c\u043e\u043b\u043e\u0433\u0438","r":"etimologi","s":0.8128},"army":{"f":"\u0430\u0440\u043c\u0438","r":"armi","s":0.8125},"nylon":{"f":"\u1828\u1822\u182f\u1823\u1828","r":"nilon","s":0.8033},"laser":{"f":"\u043b\u0430\u0437\u0435\u0440","r":"lazer","s":0.7967},"trump":{"f":"\u0442\u0440\u0430\u043c\u043f","r":"tramp","s":0.7967},"moldova":{"f":"\u043c\u043e\u043b\u0434\u0430\u0432","r":"moldav","s":0.7935},"office":{"f":"\u043e\u0444\u0444\u0438\u0441","r":"offis","s":0.785},"academy":{"f":"\u0430\u043a\u0430\u0434\u0435\u043c\u0438","r":"akademi","s":0.7673},"telephone":{"f":"\u0442\u0435\u043b\u0435\u0444\u043e\u043d","r":"telefon","s":0.7651},"catalonia":{"f":"\u043a\u0430\u0442\u0430\u043b\u043e\u043d\u0438","r":"kataloni","s":0.7468},"astronaut":{"f":"\u0430\u0441\u0442\u0440\u043e\u043d\u0430\u0432\u0442","r":"astronavt","s":0.7433},"vienna":{"f":"\u0432\u0435\u043d\u0430","r":"vena","s":0.7417},"marx":{"f":"\u043c\u0430\u0440\u043a\u0441","r":"marks","s":0.7346},"luxembourg":{"f":"\u043b\u044e\u043a\u0441\u0435\u043c\u0431\u0443\u0440\u0433","r":"liuksemburg","s":0.7342},"marxism":{"f":"\u043c\u0430\u0440\u043a\u0441\u0438\u0437\u043c","r":"marksizm","s":0.7218},"theorem":{"f":"\u0442\u0435\u043e\u0440\u0435\u043c","r":"teorem","s":0.7214},"israel":{"f":"\u0438\u0437\u0440\u0430\u0438\u043b\u044c","r":"izrail","s":0.7111},"platinum":{"f":"\u043f\u043b\u0430\u0442\u0438\u043d","r":"platin","s":0.7048},"volleyball":{"f":"\u0432\u043e\u043b\u0435\u0439\u0431\u043e\u043b","r":"voleibol","s":0.7035},"club":{"f":"\u043a\u043b\u0443\u0431","r":"klub","s":0.7},"tyumen":{"f":"\u0442\u04af\u043c\u044d\u043d","r":"tumen","s":0.6992},"hiroshima":{"f":"\u0445\u0438\u0440\u043e\u0448\u0438\u043c\u0430","r":"khiroshima","s":0.6879},"scooter":{"f":"\u0441\u043a\u0443\u0442\u0435\u0440","r":"skuter","s":0.6856},"hiragana":{"f":"\u0445\u0438\u0440\u0430\u0433\u0430\u043d\u0430","r":"khiragana","s":0.6822},"florence":{"f":"\u0444\u043b\u043e\u0440\u0435\u043d\u0446","r":"florents","s":0.6806},"catalogue":{"f":"\u043a\u0430\u0442\u0430\u043b\u043e\u0433","r":"katalog","s":0.6798},"spaghetti":{"f":"\u0448\u043f\u0430\u0433\u0435\u0442\u0442\u0438","r":"shpagetti","s":0.6758},"battery":{"f":"\u182a\u1820\u1832\u180b\u1820\u1837\u1827\u1822","r":"batareei","s":0.6667},"mannequin":{"f":"\u043c\u0430\u043d\u0435\u043a\u0435\u043d","r":"maneken","s":0.6599},"anthropomorphism":{"f":"\u0430\u043d\u0442\u0440\u043e\u043f\u043e\u043c\u043e\u0440\u0444\u0438\u0437\u043c","r":"antropomorfizm","s":0.6508},"soyuz":{"f":"\u0441\u043e\u044e\u0437","r":"soiuz","s":0.6467},"diagnosis":{"f":"\u0434\u0438\u0430\u0433\u043d\u043e\u0437","r":"diagnoz","s":0.6456},"holland":{"f":"\u0433\u043e\u043b\u043b\u0430\u043d\u0434","r":"golland","s":0.6381},"archaeology":{"f":"\u0430\u0440\u0445\u0435\u043e\u043b\u043e\u0433\u0438","r":"arkheologi","s":0.6285},"foot":{"f":"\u0444\u0443\u0442","r":"fut","s":0.625},"pope":{"f":"\u043f\u0430\u043f","r":"pap","s":0.625},"jesus":{"f":"\u0435\u0441\u04af\u0441","r":"esus","s":0.6217},"american":{"f":"\u0430\u043c\u0435\u0440\u0438\u043a","r":"amerik","s":0.6193},"hamlet":{"f":"\u0433\u0430\u043c\u043b\u0435\u0442","r":"gamlet","s":0.6189},"cairo":{"f":"\u043a\u0430\u0438\u0440","r":"kair","s":0.6183},"conclave":{"f":"\u043a\u043e\u043d\u043a\u043b\u0430\u0432","r":"konklav","s":0.6112},"skopje":{"f":"\u0441\u043a\u043e\u043f\u044c\u0435","r":"skope","s":0.6033},"atheism":{"f":"\u0430\u0442\u0435\u0438\u0437\u043c","r":"ateizm","s":0.5992},"ottawa":{"f":"\u043e\u0442\u0442\u0430\u0432\u0430","r":"ottava","s":0.5929},"ethiopia":{"f":"\u044d\u0442\u0438\u043e\u043f","r":"etiop","s":0.5875},"bodhisattva":{"f":"\u0431\u043e\u0434\u044c\u0441\u0430\u0434\u0432\u0430","r":"bodsadva","s":0.5831},"architect":{"f":"\u0430\u0440\u0445\u0438\u0442\u0435\u043a\u0442\u043e\u0440","r":"arkhitektor","s":0.5785},"accordion":{"f":"\u0430\u043a\u043a\u043e\u0440\u0434\u0435\u043e\u043d","r":"akkordeon","s":0.5769},"yogyakarta":{"f":"\u0439\u043e\u0433\u044c\u044f\u043a\u0430\u0440\u0442\u0430","r":"iogiakarta","s":0.5733},"lymph":{"f":"\u043b\u0438\u043c\u0444\u0430","r":"limfa","s":0.57},"bomb":{"f":"\u0431\u04e9\u043c\u0431\u04e9\u0433","r":"bombog","s":0.5667},"xi":{"f":"\u1830\u1822","r":"si","s":0.5667},"quebec":{"f":"\u043a\u044d\u0431\u044d\u043a","r":"kebek","s":0.5536},"yugoslavia":{"f":"\u044e\u0433\u043e\u0441\u043b\u0430\u0432","r":"iugoslav","s":0.5524},"ryan":{"f":"\u0440\u0430\u0439\u0430\u043d","r":"raian","s":0.5379},"beijing":{"f":"\u182a\u1821\u182d\u1821\u1835\u1822\u1829","r":"begejing","s":0.537},"france":{"f":"\u0444\u0440\u0430\u043d\u0446","r":"frants","s":0.5262},"tehran":{"f":"\u0442\u0435\u0433\u0435\u0440\u0430\u043d","r":"tegeran","s":0.5207},"harry":{"f":"\u0445\u0430\u0440\u0440\u0438","r":"kharri","s":0.5172},"oroqen":{"f":"\u043e\u0440\u0447\u043e\u043d","r":"orchon","s":0.5167},"moscow":{"f":"\u182e\u1823\u1830\u183b\u1838\u1820","r":"moskhawa","s":0.5144},"hungarian":{"f":"\u0443\u043d\u0433\u0430\u0440","r":"ungar","s":0.4788},"mayonnaise":{"f":"\u043c\u0430\u0439\u043e\u043d\u0435\u0437","r":"maionez","s":0.4776},"capitulation":{"f":"\u043a\u0430\u043f\u0438\u0442\u0443\u043b\u044f\u0446\u0438","r":"kapituliatsi","s":0.4741},"cent":{"f":"\u0446\u0435\u043d\u0442","r":"tsent","s":0.4683},"champagne":{"f":"\u0448\u0430\u043c\u043f\u0430\u043d\u0441\u043a","r":"shampansk","s":0.4581},"rhombus":{"f":"\u0440\u043e\u043c\u0431","r":"romb","s":0.4548},"geneva":{"f":"\u0436\u0435\u043d\u0435\u0432","r":"zhenev","s":0.454},"algeria":{"f":"\u0430\u043b\u0436\u0438\u0440","r":"alzhir","s":0.4471},"ottoman":{"f":"\u043e\u0441\u043c\u0430\u043d","r":"osman","s":0.4421},"genoa":{"f":"\u0436\u0435\u043d\u043e\u0432\u0430","r":"zhenova","s":0.4369},"eurovision":{"f":"\u0435\u0432\u0440\u043e\u0432\u0438\u0436\u043d","r":"evrovizhn","s":0.4366},"crimea":{"f":"\u043a\u0440\u044b\u043c","r":"krym","s":0.4361},"buddha":{"f":"\u0431\u0443\u0440\u0445\u0430\u043d","r":"burkhan","s":0.4357},"cheesecake":{"f":"\u0447\u0438\u0439\u0437\u043a\u044d\u0439\u043a","r":"chiizkeik","s":0.4312},"human":{"f":"\u182c\u1826\u182e\u1826\u1828","r":"qumun","s":0.4276},"mauritius":{"f":"\u043c\u0430\u0432\u0440\u0438\u043a\u0438\u0439","r":"mavrikii","s":0.4219},"station":{"f":"\u1830\u1832\u180b\u1820\u1828\u183c\u1822","r":"stantsi","s":0.4208},"toilet":{"f":"\u043d\u043e\u0439\u043b","r":"noil","s":0.4142},"philosopher":{"f":"\u0444\u0438\u043b\u043e\u0441\u043e\u0444\u0438\u0447","r":"filosofich","s":0.4021},"half":{"f":"\u0442\u0430\u043b","r":"tal","s":0.3931},"thames":{"f":"\u0442\u0435\u043c\u0437\u0430","r":"temza","s":0.3889},"england":{"f":"\u0430\u043d\u0433\u043b\u0438","r":"angli","s":0.3833},"riyadh":{"f":"\u044d\u0440-\u0440\u0438\u044f\u0434","r":"erriiad","s":0.3802},"tea":{"f":"\u0446\u0430\u0439","r":"tsai","s":0.375},"onion":{"f":"\u0441\u043e\u043d\u0433\u0438\u043d\u043e","r":"songino","s":0.3744},"orphan":{"f":"\u04e9\u043d\u0447\u0438\u043d","r":"onchin","s":0.3667},"whiskey":{"f":"\u0432\u0438\u0441\u043a\u0438","r":"viski","s":0.3655},"hades":{"f":"\u0430\u0434","r":"ad","s":0.365},"brown":{"f":"\u0431\u043e\u0440","r":"bor","s":0.345},"tomato":{"f":"\u043f\u043e\u043c\u0438\u0434\u043e\u0440","r":"pomidor","s":0.3433},"take":{"f":"\u0430\u0432\u0430\u0445","r":"avakh","s":0.335},"dance":{"f":"\u0442\u0430\u043d\u0446","r":"tants","s":0.3343},"cotton":{"f":"\u0445\u04e9\u0432\u04e9\u043d","r":"khovon","s":0.3278},"strap":{"f":"\u0441\u0443\u0440","r":"sur","s":0.3222},"teach":{"f":"\u0437\u0430\u0430\u0445","r":"zaakh","s":0.32},"cream":{"f":"\u04e9\u0440\u04e9\u043c","r":"orom","s":0.3183},"kite":{"f":"\u1821\u182f\u1822\u1836\u180e\u1821","r":"eliye","s":0.3183},"soup":{"f":"\u1831\u1825\u182f\u1826","r":"sholu","s":0.3183},"there":{"f":"\u0442\u044d\u043d\u0434","r":"tend","s":0.3183},"title":{"f":"\u0446\u043e\u043b","r":"tsol","s":0.3183},"japanese":{"f":"\u044f\u043f\u043e\u043d","r":"iapon","s":0.3183},"namesake":{"f":"\u0430\u043c\u044c\u0434\u0430\u0439","r":"amdai","s":0.3183},"jurassic":{"f":"\u044e\u0440\u0438\u0439\u043d","r":"iuriin","s":0.3153},"chord":{"f":"\u0445\u04e9\u0432\u0447","r":"khovch","s":0.3147},"dirt":{"f":"\u0445\u0438\u0440","r":"khir","s":0.3117},"pill":{"f":"\u1826\u1837\u1822\u182f","r":"uril","s":0.3117},"animate":{"f":"\u0430\u043c\u044c\u0442\u0430\u0439","r":"amtai","s":0.3055},"dust":{"f":"\u1832\u1823\u182d\u1824\u1830\u1824","r":"togusu","s":0.3004},"grip":{"f":"\u0431\u0430\u0440\u0438\u0443\u043b","r":"bariul","s":0.3004},"pain":{"f":"\u04e9\u0432\u0447\u0438\u043d","r":"ovchin","s":0.3004},"when":{"f":"\u0445\u044d\u0437\u044d\u044d","r":"khezee","s":0.3004},"bug":{"f":"\u0431\u044f\u0441\u0430\u0430","r":"biasaa","s":0.3},"heaven":{"f":"\u0442\u044d\u043d\u0433\u044d\u0440","r":"tenger","s":0.3},"remorse":{"f":"\u0433\u044d\u043c\u0448\u0438\u043b","r":"gemshil","s":0.2996},"morning":{"f":"\u1825\u1837\u182f\u1826\u182d\u1821","r":"orluge","s":0.2993},"peach":{"f":"\u043f\u0435\u0440\u0441\u0438\u043a","r":"persik","s":0.2986},"beryl":{"f":"\u0431\u0438\u043d\u0434\u044d\u0440\u044a\u044f\u0430","r":"binderiaa","s":0.298},"garden":{"f":"\u0445\u04af\u0440\u044d\u044d\u043b\u044d\u043d","r":"khureelen","s":0.2944},"monster":{"f":"\u043c\u0430\u043d\u0433\u0430\u0441","r":"mangas","s":0.2893},"bottom":{"f":"\u0451\u0440\u043e\u043e\u043b","r":"iorool","s":0.2889},"number":{"f":"\u0434\u0443\u0433\u0430\u0430\u0440","r":"dugaar","s":0.2889},"bench":{"f":"\u0431\u0430\u043d\u0434\u0430\u043d","r":"bandan","s":0.2861},"tacheng":{"f":"\u0447\u04e9\u0432\u0447\u04e9\u0433","r":"chovchog","s":0.279},"hydrogen":{"f":"\u0443\u0441\u0442\u04e9\u0440\u04e9\u0433\u0447","r":"ustorogch","s":0.2786},"air":{"f":"\u0430\u0433\u0430\u0430\u0440","r":"agaar","s":0.2778},"naturalist":{"f":"\u0431\u0430\u0439\u0433\u0430\u043b\u044c\u0447","r":"baigalch","s":0.2762},"chinese":{"f":"\u0445\u044f\u0442\u0430\u0434","r":"khiatad","s":0.2758},"bald":{"f":"\u0445\u0430\u043b\u0437\u0430\u043d","r":"khalzan","s":0.2756},"bridge":{"f":"\u182d\u1826\u182d\u1826\u1837\u182d\u1821","r":"gugurge","s":0.2746},"ounce":{"f":"\u0443\u043d\u0446\u0438","r":"untsi","s":0.2743},"aggressive":{"f":"\u0442\u04af\u0440\u044d\u043c\u0433\u0438\u0439","r":"turemgii","s":0.2742},"today":{"f":"\u04e9\u043d\u04e9\u04e9\u0434\u04e9\u0440","r":"onoodor","s":0.273},"scribe":{"f":"\u182a\u1822\u1834\u1822\u182d\u1821\u1834\u1822","r":"bichigechi","s":0.2714},"larva":{"f":"\u0430\u0432\u0433\u0430\u043b\u0434\u0430\u0439","r":"avgaldai","s":0.2708},"translator":{"f":"\u043e\u0440\u0447\u0443\u0443\u043b\u0430\u0433\u0447","r":"orchuulagch","s":0.2708},"nation":{"f":"\u04af\u043d\u0434\u044d\u0441\u0442\u044d\u043d","r":"undesten","s":0.2687},"egg":{"f":"\u1825\u1828\u1833\u1821\u182d\u1821","r":"ondege","s":0.2667},"attack":{"f":"\u0434\u0430\u0439\u0440\u0430\u043b\u0442","r":"dairalt","s":0.2635},"bracket":{"f":"\u0445\u0430\u0430\u043b\u0442","r":"khaalt","s":0.2635},"council":{"f":"\u0437\u04e9\u0432\u043b\u04e9\u043b","r":"zovlol","s":0.2635},"current":{"f":"\u0433\u04af\u0439\u0434\u044d\u043b","r":"guidel","s":0.2635},"sulfur":{"f":"\u0445\u04af\u0445\u044d\u0440","r":"khukher","s":0.2635},"bear":{"f":"\u0431\u0430\u0430\u0432\u0433\u0430\u0439","r":"baavgai","s":0.2631},"risk":{"f":"\u1821\u1837\u1826\u1830\u1833\u1821\u182f","r":"erusdel","s":0.2631},"dark":{"f":"\u0445\u0430\u0440\u0430\u043d\u0445\u0443\u0439","r":"kharankhui","s":0.2631},"beast":{"f":"\u0430\u0440\u0430\u0430\u0442\u0430\u043d","r":"araatan","s":0.2619},"evening":{"f":"\u1826\u1833\u1821\u1830\u1822","r":"udesi","s":0.2619},"green":{"f":"\u1828\u1823\u182d\u1824\u182d\u1820\u1828","r":"nogugan","s":0.2619},"model":{"f":"\u043c\u0430\u043d\u0435\u043a\u0435\u043d","r":"maneken","s":0.2619},"storm":{"f":"\u0448\u0443\u0443\u0440\u0433\u0430","r":"shuurga","s":0.2619},"muscle":{"f":"\u0431\u0443\u043b\u0447\u0438\u043d","r":"bulchin","s":0.2615},"pregnant":{"f":"\u0436\u0438\u0440\u044d\u043c\u0441\u044d\u043d","r":"zhiremsen","s":0.2606},"garbage":{"f":"\u0445\u0430\u044f\u0433\u0434\u0430\u043b","r":"khaiagdal","s":0.2601},"train":{"f":"\u0432\u0430\u0433\u043e\u043d","r":"vagon","s":0.26},"gray":{"f":"\u0441\u0430\u0430\u0440\u0430\u043b","r":"saaral","s":0.2587},"play":{"f":"\u1832\u1823\u182d\u182f\u1820\u182d\u1820\u182e","r":"toglagam","s":0.2569},"reading":{"f":"\u1824\u1829\u1830\u1822\u182f\u182d\u180e\u1820","r":"ungsilga","s":0.2551},"squirrel":{"f":"\u0445\u044d\u0440\u044d\u043c","r":"kherem","s":0.2535},"qinghai":{"f":"\u182c\u1825\u182c\u1821\u1828\u1820\u182d\u1824\u1837","r":"qoqenagur","s":0.2527},"time":{"f":"\u0446\u0430\u0433","r":"tsag","s":0.25},"reach":{"f":"\u0445\u04af\u0440\u044d\u0445","r":"khurekh","s":0.2458},"declaration":{"f":"\u0437\u0430\u0440\u043b\u0430\u043b","r":"zarlal","s":0.2456},"anecdote":{"f":"\u043e\u043d\u0438\u0433\u043e\u043e","r":"onigoo","s":0.2444},"can":{"f":"\u043b\u0430\u0430\u0437","r":"laaz","s":0.2444},"comb":{"f":"\u0441\u0430\u043c","r":"sam","s":0.2444},"day":{"f":"\u04e9\u0434\u04e9\u0440","r":"odor","s":0.2444},"era":{"f":"\u0446\u0430\u0433","r":"tsag","s":0.2444},"here":{"f":"\u044d\u043d\u0434","r":"end","s":0.2444},"hip":{"f":"\u0433\u0443\u044f","r":"guia","s":0.2444},"man":{"f":"\u0445\u04af\u043d","r":"khun","s":0.2444},"raft":{"f":"\u0441\u0430\u043b","r":"sal","s":0.2444},"tael":{"f":"\u043b\u0430\u043d","r":"lan","s":0.2444},"that":{"f":"\u0442\u044d\u0440","r":"ter","s":0.2444},"war":{"f":"\u0434\u0430\u0439\u043d","r":"dain","s":0.2444},"who":{"f":"\u0445\u044d\u043d","r":"khen","s":0.2444},"break":{"f":"\u0437\u04e9\u0440\u0447\u0438\u0445","r":"zorchikh","s":0.2437},"civilian":{"f":"\u0438\u0440\u0433\u044d\u043d","r":"irgen","s":0.2437},"clerk":{"f":"\u0431\u0438\u0447\u044d\u044d\u0447","r":"bicheech","s":0.2437},"concrete":{"f":"\u0431\u043e\u0434\u0438\u0442","r":"bodit","s":0.2437},"mountain":{"f":"\u1820\u182d\u1824\u182f\u1820","r":"agula","s":0.2437},"smell":{"f":"\u04af\u043d\u044d\u0440\u043b\u044d\u0445","r":"unerlekh","s":0.2437},"sister-in-law":{"f":"\u0431\u044d\u0440\u0433\u044d\u043d","r":"bergen","s":0.2428},"cleaner":{"f":"\u0446\u044d\u0432\u044d\u0440\u043b\u044d\u0433\u0447","r":"tseverlegch","s":0.2424},"bury":{"f":"\u0431\u0443\u043b\u0448\u043b\u0430\u0445","r":"bulshlakh","s":0.2424},"turquoise":{"f":"\u043e\u044e\u0443","r":"oiuu","s":0.2424},"valerian":{"f":"\u0431\u0430\u043c\u0431\u0430\u0439","r":"bambai","s":0.241},"female":{"f":"\u044d\u043c\u044d\u0433\u0447\u0438\u043d","r":"emegchin","s":0.2403},"intestine":{"f":"\u0433\u044d\u0434\u044d\u0441","r":"gedes","s":0.2396},"department":{"f":"\u0445\u044d\u043b\u0442\u044d\u0441","r":"kheltes","s":0.239},"brain":{"f":"\u0442\u0430\u0440\u0445\u0438","r":"tarkhi","s":0.2389},"palate":{"f":"\u0442\u0430\u0433\u043d\u0430\u0439","r":"tagnai","s":0.2389},"court":{"f":"\u0445\u043e\u0440\u043e\u043e","r":"khoroo","s":0.2361},"please":{"f":"-\u044d\u044d\u0440\u044d\u0439","r":"eerei","s":0.2361},"whose":{"f":"\u0445\u044d\u043d\u0438\u0439","r":"khenii","s":0.2361},"sailor":{"f":"\u0434\u0430\u043b\u0430\u0439\u0447\u0438\u043d","r":"dalaichin","s":0.2333},"jack":{"f":"\u0434\u0430\u043d\u0445\u0440\u0430\u0430\u0442","r":"dankhraat","s":0.2324},"ephedra":{"f":"\u0437\u044d\u044d\u0440\u0433\u044d\u043d\u044d","r":"zeergene","s":0.2315},"cabinet":{"f":"\u0448\u0457\u0457\u0433\u044d\u044d","r":"shyiyigee","s":0.2312},"sacrifice":{"f":"\u0442\u0430\u0445\u0438\u0445","r":"takhikh","s":0.2312},"dictionary":{"f":"\u0442\u043e\u043b\u044c","r":"tol","s":0.2306},"acid":{"f":"\u0445\u04af\u0447\u0438\u043b","r":"khuchil","s":0.2304},"canteen":{"f":"\u0433\u0443\u0430\u043d\u0437","r":"guanz","s":0.2302},"labour":{"f":"\u0445\u04e9\u0434\u04e9\u043b\u043c\u04e9\u0440","r":"khodolmor","s":0.2296},"layer":{"f":"\u0434\u0430\u0432\u0445\u0430\u0440\u0433\u0430","r":"davkharga","s":0.2296},"hit":{"f":"\u0446\u043e\u0445\u0438\u0445","r":"tsokhikh","s":0.2296},"create":{"f":"\u0431\u04af\u0442\u044d\u044d\u0445","r":"buteekh","s":0.2287},"substance":{"f":"\u182a\u1823\u1833\u1820\u1830","r":"bodas","s":0.2278},"apple":{"f":"\u1820\u182f\u1822\u182e\u180e\u1820","r":"alima","s":0.2267},"force":{"f":"\u0445\u04af\u0447","r":"khuch","s":0.2267},"ready":{"f":"\u0431\u044d\u043b\u044d\u043d","r":"belen","s":0.2267},"south":{"f":"\u1821\u182e\u1826\u1828\u180e\u1821","r":"emune","s":0.2267},"watch":{"f":"\u04af\u0437\u044d\u0445","r":"uzekh","s":0.2267},"wheel":{"f":"\u0445\u04af\u0440\u0434","r":"khurd","s":0.2267},"cinderella":{"f":"\u04af\u043d\u0441\u0433\u044d\u043b\u0436\u0438\u043d","r":"unsgelzhin","s":0.2258},"hangover":{"f":"\u0445\u043e\u0446\u0440\u043e\u0433\u0434\u043e\u043b","r":"khotsrogdol","s":0.2254},"liberate":{"f":"\u1834\u1822\u182f\u1826\u182d\u1821\u182f\u1821\u182c\u1826","r":"chilugelequ","s":0.2254},"reason":{"f":"\u0448\u0430\u043b\u0442\u0433\u0430\u0430\u043d","r":"shaltgaan","s":0.225},"user":{"f":"\u0445\u044d\u0440\u044d\u0433\u043b\u044d\u0433\u0447","r":"khereglegch","s":0.222},"boil":{"f":"\u0431\u0443\u0446\u0430\u043b\u0433\u0430\u0445","r":"butsalgakh","s":0.2217},"fruit":{"f":"\u04af\u0440","r":"ur","s":0.2217},"grain":{"f":"\u04af\u0440","r":"ur","s":0.2217},"woman":{"f":"\u044d\u043c","r":"em","s":0.2217},"among":{"f":"\u0434\u0443\u043d\u0434","r":"dund","s":0.2208},"drop":{"f":"\u0434\u0443\u0441\u0430\u043b","r":"dusal","s":0.2208},"east":{"f":"\u1835\u1821\u182d\u1826\u1828","r":"jegun","s":0.2208},"exit":{"f":"\u0433\u0430\u0440\u0446","r":"garts","s":0.2208},"foam":{"f":"\u0445\u04e9\u04e9\u0441","r":"khoos","s":0.2208},"grow":{"f":"\u04e9\u0441\u04e9\u0445","r":"osokh","s":0.2208},"jade":{"f":"\u0445\u0430\u0448","r":"khash","s":0.2208},"king":{"f":"\u043d\u043e\u0451\u043d","r":"noion","s":0.2208},"lake":{"f":"\u1828\u1820\u182d\u1824\u1837","r":"nagur","s":0.2208},"mind":{"f":"\u043e\u044e\u0443\u043d","r":"oiuun","s":0.2208},"open":{"f":"\u043d\u044d\u044d\u0445","r":"neekh","s":0.2208},"rich":{"f":"\u0431\u0430\u044f\u043d","r":"baian","s":0.2208},"sheep":{"f":"\u0445\u043e\u043d\u044c","r":"khon","s":0.2208},"wolf":{"f":"\u0447\u043e\u043d\u043e","r":"chono","s":0.2208},"arrive":{"f":"\u0445\u04af\u0440\u044d\u0445","r":"khurekh","s":0.2206},"diamond":{"f":"\u0430\u043b\u043c\u0430\u0430\u0437","r":"almaaz","s":0.2206},"eraser":{"f":"\u0431\u0430\u043b\u043b\u0443\u0443\u0440","r":"balluur","s":0.2206},"forward":{"f":"\u0443\u0440\u0430\u0433\u0448","r":"uragsh","s":0.2206},"screen":{"f":"\u0434\u044d\u043b\u0433\u044d\u0446","r":"delgets","s":0.2206},"stroke":{"f":"\u0442\u0430\u0430\u043b\u0430\u0445","r":"taalakh","s":0.2206},"turnip":{"f":"\u043c\u0430\u043d\u0436\u0438\u043d","r":"manzhin","s":0.2206},"country":{"f":"\u043e\u0440\u043e\u043d","r":"oron","s":0.2202},"wing":{"f":"\u0436\u0438\u0433\u04af\u04af\u0440","r":"zhiguur","s":0.2202},"backward":{"f":"\u0430\u0440\u0430\u043d\u0448\u0430\u0430","r":"aranshaa","s":0.2202},"density":{"f":"\u043d\u044f\u0433\u0442","r":"niagt","s":0.219},"grammar":{"f":"\u0434\u04af\u0440\u044d\u043c","r":"durem","s":0.219},"meter":{"f":"\u0442\u043e\u043e\u043b\u0443\u0443\u0440","r":"tooluur","s":0.219},"pregnancy":{"f":"\u0436\u0438\u0440\u044d\u043c\u0441\u043b\u044d\u043b\u0442","r":"zhiremslelt","s":0.2183},"supplicate":{"f":"\u0433\u0443\u0439\u0445","r":"guikh","s":0.2183},"ask":{"f":"\u0433\u0443\u0439\u0445","r":"guikh","s":0.2178},"bee":{"f":"\u1835\u1825\u182d\u1821\u1822","r":"jogei","s":0.2178},"dog":{"f":"\u1828\u1823\u182c\u1820\u1822","r":"noqai","s":0.2178},"korean":{"f":"\u0441\u043e\u043b\u043e\u043d\u0433\u043e\u0441\u044b\u043d","r":"solongosyn","s":0.2178},"law":{"f":"\u182c\u1820\u1824\u182f\u1822","r":"qauli","s":0.2178},"run":{"f":"\u0433\u04af\u0439\u0445","r":"guikh","s":0.2178},"sea":{"f":"\u0434\u0430\u043b\u0430\u0439","r":"dalai","s":0.2178},"see":{"f":"\u04af\u0437\u044d\u0445","r":"uzekh","s":0.2178},"understand":{"f":"\u0443\u0445\u0430\u0445","r":"ukhakh","s":0.2178},"portrait":{"f":"\u0445\u04e9\u0440\u04e9\u0433","r":"khorog","s":0.216},"dash":{"f":"\u0437\u0443\u0440\u0430\u0430\u0441","r":"zuraas","s":0.2157},"explain":{"f":"\u0442\u0430\u0439\u043b\u0431\u0430\u0440\u043b\u0430\u0445","r":"tailbarlakh","s":0.2146},"bean":{"f":"\u0431\u0443\u0443\u0440\u0446\u0430\u0433","r":"buurtsag","s":0.2146},"profession":{"f":"\u043c\u044d\u0440\u0433\u044d\u0436\u0438\u043b","r":"mergezhil","s":0.2133},"shepherd":{"f":"\u0445\u043e\u043d\u044c\u0447\u0438\u043d","r":"khonchin","s":0.2125},"watermelon":{"f":"\u0442\u0430\u0440\u0432\u0430\u0441","r":"tarvas","s":0.2122},"concentration":{"f":"\u0430\u043d\u0445\u0430\u0430\u0440\u0430\u043b","r":"ankhaaral","s":0.212},"accent":{"f":"\u0430\u044f\u043b\u0433\u0430","r":"aialga","s":0.2111},"buckle":{"f":"\u0433\u043e\u0440\u0445\u0438","r":"gorkhi","s":0.2111},"coffee":{"f":"\u0431\u043e\u0440\u0433\u043e\u043b","r":"borgol","s":0.2111},"daikon":{"f":"\u043b\u0443\u0443\u0432\u0430\u043d","r":"luuvan","s":0.2111},"season":{"f":"\u1824\u182f\u1820\u1837\u1822\u182f","r":"ularil","s":0.2111},"symbol":{"f":"\u0442\u044d\u043c\u0434\u044d\u0433","r":"temdeg","s":0.2111},"system":{"f":"\u0436\u0443\u0440\u0430\u043c","r":"zhuram","s":0.2111},"loudspeaker":{"f":"\u04e9\u0441\u0433\u04e9\u0433\u0447","r":"osgogch","s":0.2087},"russification":{"f":"\u043e\u0440\u043e\u0441\u0436\u0443\u0443\u043b\u0430\u0445","r":"oroszhuulakh","s":0.2082},"lychee":{"f":"\u043d\u0435\u0444\u0435\u043b\u0435\u0443\u043c","r":"nefeleum","s":0.2069},"sinner":{"f":"\u043d\u04af\u0433\u044d\u043b\u0442\u044d\u043d","r":"nugelten","s":0.2069},"repeatability":{"f":"\u0442\u043e\u0445\u0438\u0440\u0446","r":"tokhirts","s":0.2067},"angle":{"f":"\u04e9\u043d\u0446\u04e9\u0433","r":"ontsog","s":0.2056},"barrel":{"f":"\u0442\u043e\u0440\u0445","r":"torkh","s":0.2056},"bottle":{"f":"\u043b\u043e\u043d\u0445","r":"lonkh","s":0.2056},"clean":{"f":"\u0446\u044d\u0432\u044d\u0440","r":"tsever","s":0.2056},"north":{"f":"\u182c\u1823\u1836\u1822\u1833\u1824","r":"qoyidu","s":0.2056},"pendulum":{"f":"\u1833\u1821\u182d\u1826\u1835\u1822\u1829","r":"degujing","s":0.2056},"person":{"f":"\u182c\u1826\u182e\u1826\u1828","r":"qumun","s":0.2056},"strip":{"f":"\u0437\u0443\u0440\u0432\u0430\u0441","r":"zurvas","s":0.2056},"swear":{"f":"\u0430\u043c\u043b\u0430\u0445","r":"amlakh","s":0.2056},"where":{"f":"\u0445\u0430\u0430\u043d\u0430","r":"khaana","s":0.2056},"participant":{"f":"\u043e\u0440\u043e\u043b\u0446\u043e\u0433\u0447","r":"oroltsogch","s":0.2038},"candidate":{"f":"\u1833\u1821\u182a\u1830\u1822\u182d\u1834\u1822","r":"debsigchi","s":0.2037},"modality":{"f":"\u0431\u0430\u0439\u043c\u0436","r":"baimzh","s":0.2035},"translation":{"f":"\u043e\u0440\u0447\u0443\u0443\u043b\u0433\u0430","r":"orchuulga","s":0.202},"dress":{"f":"\u0445\u0443\u0432\u0446\u0430\u0441\u043b\u0430\u0445","r":"khuvtsaslakh","s":0.2014},"baby":{"f":"\u043c\u0430\u0430\u043c\u0443\u0443","r":"maamuu","s":0.2014},"ball":{"f":"\u0431\u04e9\u043c\u0431\u04e9\u0433","r":"bombog","s":0.2014},"basket":{"f":"\u0430\u0440\u0430\u0433","r":"arag","s":0.2014},"degree":{"f":"\u0445\u044d\u043c","r":"khem","s":0.2014},"desert":{"f":"\u0446\u04e9\u043b","r":"tsol","s":0.2014},"know":{"f":"\u0442\u0430\u043d\u0438\u0445","r":"tanikh","s":0.2014},"lion":{"f":"\u0430\u0440\u0441\u043b\u0430\u043d","r":"arslan","s":0.2014},"lose":{"f":"\u0430\u043b\u0434\u0430\u0445","r":"aldakh","s":0.2014},"mother":{"f":"\u044d\u044d\u0436","r":"eezh","s":0.2014},"ours":{"f":"\u182e\u1820\u1828\u180b\u1824\u182c\u1822","r":"manuqi","s":0.2014},"race":{"f":"\u04af\u04af\u043b\u0434\u044d\u0440","r":"uulder","s":0.2014},"rest":{"f":"\u0430\u043c\u0440\u0430\u0445","r":"amrakh","s":0.2014},"shut":{"f":"\u0445\u0430\u0430\u0445","r":"khaakh","s":0.2014},"tongue":{"f":"\u182c\u1821\u182f\u1821","r":"qele","s":0.2014},"wild":{"f":"\u0437\u044d\u0440\u043b\u044d\u0433","r":"zerleg","s":0.2014},"comparison":{"f":"\u0445\u0430\u0440\u044c\u0446\u0443\u0443\u043b\u0430\u043b\u0442","r":"khartsuulalt","s":0.2011},"carnivore":{"f":"\u043c\u0430\u0445\u0447\u0438\u043d","r":"makhchin","s":0.2005},"hamster":{"f":"\u0448\u0438\u0448\u04af\u04af\u0445\u044d\u0439","r":"shishuukhei","s":0.2004},"command":{"f":"\u0442\u0443\u0448\u0430\u0430\u043b","r":"tushaal","s":0.2},"dharma":{"f":"\u043d\u043e\u043c","r":"nom","s":0.2},"die":{"f":"\u04af\u0445\u044d\u0445","r":"ukhekh","s":0.2},"temple":{"f":"\u0441\u04af\u043c","r":"sum","s":0.2},"vessel":{"f":"\u0441\u0430\u0432","r":"sav","s":0.2},"beautiful":{"f":"\u0441\u0430\u0439\u0445\u0430\u043d","r":"saikhan","s":0.1979},"cookie":{"f":"\u0436\u0438\u0433\u043d\u044d\u043c\u044d\u0433","r":"zhignemeg","s":0.1963},"hiccup":{"f":"\u1835\u1823\u182d\u1822\u1830\u1824\u182f\u1832\u1820","r":"jogisulta","s":0.1963},"killer":{"f":"\u0430\u043b\u0443\u0443\u0440\u0447\u0438\u043d","r":"aluurchin","s":0.1963},"persimmon":{"f":"\u0445\u0443\u0440\u043c\u0430","r":"khurma","s":0.1963},"saddle":{"f":"\u044d\u043c\u044d\u044d\u043b\u043b\u044d\u0445","r":"emeellekh","s":0.1963},"artist":{"f":"\u0437\u0443\u0440\u0430\u0430\u0447","r":"zuraach","s":0.1948},"little":{"f":"\u0436\u0438\u0436\u0438\u0433","r":"zhizhig","s":0.1948},"outside":{"f":"\u0433\u0430\u0434\u0430\u0430\u0434","r":"gadaad","s":0.1948},"locust":{"f":"\u0433\u043e\u043b\u0438\u043e","r":"golio","s":0.1944},"spleen":{"f":"\u0434\u044d\u043b\u04af\u04af","r":"deluu","s":0.1944},"bird":{"f":"\u1830\u1822\u182a\u1820\u182d\u1824","r":"sibagu","s":0.1944},"island":{"f":"\u0430\u0440\u0430\u043b","r":"aral","s":0.1944},"robust":{"f":"\u0431\u04e9\u0445","r":"bokh","s":0.1944},"wake":{"f":"\u0441\u044d\u0440\u044d\u0445","r":"serekh","s":0.1944},"wish":{"f":"\u0445\u04af\u0441\u044d\u043b","r":"khusel","s":0.1944},"pronunciation":{"f":"\u0434\u0443\u0443\u0434\u043b\u0430\u0433\u0430","r":"duudlaga","s":0.1939},"brake":{"f":"\u0442\u043e\u043e\u0440\u043c\u043e\u0441","r":"toormos","s":0.1905},"chapter":{"f":"\u0431\u04af\u043b\u044d\u0433","r":"buleg","s":0.1905},"cheek":{"f":"\u0445\u0430\u0446\u0430\u0440","r":"khatsar","s":0.1905},"child":{"f":"\u0445\u04e9\u0432\u04af\u04af\u043d","r":"khovuun","s":0.1905},"cover":{"f":"\u0431\u04af\u0442\u044d\u044d\u0445","r":"buteekh","s":0.1905},"house":{"f":"\u0431\u0430\u0439\u0448\u0438\u043d","r":"baishin","s":0.1905},"nasal":{"f":"\u0445\u0430\u043c\u0440\u044b\u043d","r":"khamryn","s":0.1905},"headphones":{"f":"\u0447\u0438\u0445\u044d\u0432\u0447","r":"chikhevch","s":0.19},"consumer":{"f":"\u0445\u044d\u0440\u044d\u0433\u043b\u044d\u0433\u0447","r":"khereglegch","s":0.1896},"cosmos":{"f":"\u0441\u0430\u043d\u0441\u0430\u0440","r":"sansar","s":0.1889},"forgive":{"f":"\u1820\u182d\u1824\u1834\u1822\u182f\u1820\u182c\u1824","r":"aguchilaqu","s":0.1888},"hear":{"f":"\u0434\u0443\u0443\u043b\u0430\u0445","r":"duulakh","s":0.1875},"look":{"f":"\u0445\u0430\u0440\u0430\u0445","r":"kharakh","s":0.1875},"pancake":{"f":"\u182a\u1822\u1829","r":"bing","s":0.1875},"rust":{"f":"\u0437\u044d\u0432\u0442\u044d\u0445","r":"zevtekh","s":0.1875},"species":{"f":"\u0437\u04af\u0439\u043b","r":"zuil","s":0.1875},"variety":{"f":"\u0437\u04af\u0439\u043b","r":"zuil","s":0.1875},"whip":{"f":"\u0442\u0430\u0448\u0443\u0443\u0440","r":"tashuur","s":0.1875},"bag":{"f":"\u1830\u1822\u182d\u1824\u1833\u1820\u1822","r":"sigudai","s":0.1873},"brother":{"f":"\u0430\u0445","r":"akh","s":0.1873},"fry":{"f":"\u0448\u0430\u0440\u0430\u0445","r":"sharakh","s":0.1873},"decision":{"f":"\u0442\u043e\u0433\u0442\u043e\u043e\u043b","r":"togtool","s":0.1869},"responsibility":{"f":"\u182c\u1820\u1837\u1822\u182d\u1824\u1834\u1820\u182f\u182d\u180e\u1820","r":"qariguchalga","s":0.1863},"dear":{"f":"\u044d\u0440\u0445\u044d\u043c","r":"erkhem","s":0.1861},"chicken":{"f":"\u0442\u0430\u0445\u0438\u0430","r":"takhia","s":0.1858},"champion":{"f":"\u0430\u0432\u0430\u0440\u0433\u0430","r":"avarga","s":0.1826},"hunger":{"f":"\u04e9\u043b\u0441\u0433\u04e9\u043b\u04e9\u043d","r":"olsgolon","s":0.1826},"stallion":{"f":"\u0430\u0437\u0440\u0430\u0433\u0430","r":"azraga","s":0.1826},"interpretation":{"f":"\u0442\u0430\u0439\u043b\u0431\u0430\u0440\u043b\u0430\u043b","r":"tailbarlal","s":0.1821},"accident":{"f":"\u0430\u0432\u0430\u0430\u0440","r":"avaar","s":0.1792},"bread":{"f":"\u043c\u0438\u044f\u043d\u0431\u0443\u0443","r":"miianbuu","s":0.1792},"fight":{"f":"\u0431\u0430\u0439\u043b\u0434\u0430\u0445","r":"baildakh","s":0.1792},"korea":{"f":"\u0441\u043e\u043b\u043e\u043d\u0433\u043e\u0441","r":"solongos","s":0.1792},"membrane":{"f":"\u0445\u0430\u043b\u044c\u0441","r":"khals","s":0.1792},"opposite":{"f":"\u044d\u0441\u0440\u044d\u0433","r":"esreg","s":0.1792},"tower":{"f":"\u0446\u0430\u043c\u0445\u0430\u0433","r":"tsamkhag","s":0.1792},"lioness":{"f":"\u044d\u0440\u0441\u043b\u044d\u043d","r":"erslen","s":0.179},"wither":{"f":"\u0445\u0430\u0442\u0430\u0445","r":"khatakh","s":0.179},"old":{"f":"\u0445\u04e9\u0433\u0448\u0438\u043d","r":"khogshin","s":0.1778},"light":{"f":"\u0445\u04e9\u043d\u0433\u04e9\u043d","r":"khongon","s":0.1774},"wring":{"f":"\u182e\u1824\u1830\u182d\u1822\u182c\u1824","r":"musgiqu","s":0.1774},"bake":{"f":"\u0436\u0438\u0433\u043d\u044d\u0445","r":"zhignekh","s":0.1771},"blue":{"f":"\u0446\u044d\u043d\u0445\u044d\u0440","r":"tsenkher","s":0.1771},"deal":{"f":"\u0445\u0443\u0432\u0430\u0430\u0445","r":"khuvaakh","s":0.1771},"leak":{"f":"\u0433\u043e\u043e\u0436\u0438\u0445","r":"goozhikh","s":0.1771},"slaughter":{"f":"\u0445\u044f\u0434\u043b\u0430\u0433\u0430","r":"khiadlaga","s":0.177},"girl":{"f":"\u1825\u182c\u1822\u1828","r":"oqin","s":0.175},"horn":{"f":"\u044d\u0432\u044d\u0440","r":"ever","s":0.175},"hour":{"f":"\u1834\u1820\u182d","r":"chag","s":0.175},"kind":{"f":"\u0437\u04af\u0439\u043b","r":"zuil","s":0.175},"more":{"f":"\u0434\u044d\u044d\u0440","r":"deer","s":0.175},"nest":{"f":"\u1821\u182d\u1826\u1837","r":"egur","s":0.175},"snow":{"f":"\u0446\u0430\u0441","r":"tsas","s":0.175},"true":{"f":"\u04af\u043d\u044d\u043d","r":"unen","s":0.175},"enough":{"f":"\u0445\u0430\u043d\u0433\u0430\u043b\u0442\u0442\u0430\u0439","r":"khangalttai","s":0.1745},"distance":{"f":"\u0437\u0430\u0439","r":"zai","s":0.1743},"closed":{"f":"\u0445\u0430\u0430\u043b\u0442\u0442\u0430\u0439","r":"khaalttai","s":0.1731},"allergy":{"f":"\u0445\u0430\u0440\u0448\u0438\u043b","r":"kharshil","s":0.1717},"it":{"f":"\u0442\u0443\u0443\u043d","r":"tuun","s":0.1708},"jellyfish":{"f":"\u043c\u0435\u0434\u0443\u0437","r":"meduz","s":0.1704},"ignite":{"f":"\u043d\u043e\u0446\u043e\u043e\u0445","r":"notsookh","s":0.1694},"way":{"f":"\u0430\u0440\u0433\u0430","r":"arga","s":0.1694},"anus":{"f":"\u0433\u0443\u0440\u0433\u0430\u043b\u0434\u0430\u0439","r":"gurgaldai","s":0.169},"cone":{"f":"\u0431\u043e\u0440\u0433\u043e\u0446\u043e\u0439","r":"borgotsoi","s":0.169},"creator":{"f":"\u0431\u04af\u0442\u044d\u044d\u0433\u0447","r":"buteegch","s":0.1676},"grilled":{"f":"\u0445\u0430\u0439\u0440\u0441\u0430\u043d","r":"khairsan","s":0.1676},"problem":{"f":"\u0445\u04af\u043d\u0434\u0440\u044d\u043b","r":"khundrel","s":0.1676},"merchandise":{"f":"\u0431\u0430\u0440\u0430\u0430","r":"baraa","s":0.1674},"steal":{"f":"\u0445\u0443\u043b\u0433\u0430\u0439\u043b\u0430\u0445","r":"khulgailakh","s":0.1674},"cast":{"f":"\u0446\u0443\u0442\u0433\u0430\u0445","r":"tsutgakh","s":0.1667},"flax":{"f":"\u043c\u0430\u0430\u043b\u0438\u043d\u0433\u0430","r":"maalinga","s":0.1667},"heavy":{"f":"\u0445\u04af\u043d\u0434","r":"khund","s":0.1667},"juice":{"f":"\u0448\u04af\u04af\u0441","r":"shuus","s":0.1667},"sable":{"f":"\u0431\u0443\u043b\u0433\u0430","r":"bulga","s":0.1667},"wrong":{"f":"\u0431\u0443\u0440\u0443\u0443","r":"buruu","s":0.1667},"regret":{"f":"\u0445\u0430\u0440\u0430\u043c\u0441\u0430\u0445","r":"kharamsakh","s":0.1656},"sphere":{"f":"\u0431\u04e9\u043c\u0431\u04e9\u0440\u0446\u04e9\u0433","r":"bombortsog","s":0.1656},"cinnamon":{"f":"\u0448\u0430\u043d\u0446","r":"shants","s":0.1653},"nickname":{"f":"\u0445\u043e\u0447","r":"khoch","s":0.1646},"lever":{"f":"\u0445\u04e9\u0448\u04af\u04af\u0440\u044d\u0433","r":"khoshuureg","s":0.1633},"reproducibility":{"f":"\u0442\u0430\u0430\u0440\u0446","r":"taarts","s":0.1628},"thug":{"f":"\u043b\u0443\u0439\u0432\u0430\u0440\u0447\u0438\u043d","r":"luivarchin","s":0.1625},"hearts":{"f":"\u0431\u0443\u043d\u0434\u0430\u043d","r":"bundan","s":0.1611},"helmet":{"f":"\u0434\u0443\u0443\u043b\u0433\u0430","r":"duulga","s":0.1611},"orange":{"f":"\u0436\u04af\u0440\u0436","r":"zhurzh","s":0.1611},"simple":{"f":"\u044d\u043d\u0433\u0438\u0439\u043d","r":"engiin","s":0.1611},"square":{"f":"\u0442\u0430\u043b\u0431\u0430\u0439","r":"talbai","s":0.1611},"boot":{"f":"\u0433\u0443\u0442\u0430\u043b","r":"gutal","s":0.1608},"cable":{"f":"\u0443\u0442\u0430\u0441","r":"utas","s":0.1608},"come":{"f":"\u0438\u0440\u044d\u0445","r":"irekh","s":0.1608},"inflection":{"f":"\u0445\u0443\u0432\u0438\u0440\u0430\u043b","r":"khuviral","s":0.1608},"lance":{"f":"\u0436\u0430\u0434","r":"zhad","s":0.1608},"update":{"f":"\u0448\u0438\u043d\u044d\u0447\u043b\u044d\u0445","r":"shinechlekh","s":0.1593},"gland":{"f":"\u0431\u0443\u043b\u0447\u0438\u0440\u0445\u0430\u0439","r":"bulchirkhai","s":0.1576},"gout":{"f":"\u0442\u0443\u043b\u0430\u0439\u0442\u0430\u0445","r":"tulaitakh","s":0.1574},"therapy":{"f":"\u044d\u043c\u0447\u0438\u043b\u0433\u044d\u044d","r":"emchilgee","s":0.1562},"field":{"f":"\u0442\u0430\u043b\u0431\u0430\u0439","r":"talbai","s":0.1556},"rider":{"f":"\u043c\u043e\u0440\u044c\u0442\u043e\u043d","r":"morton","s":0.1556},"spring":{"f":"\u182c\u1820\u182a\u1824\u1837","r":"qabur","s":0.1556},"state":{"f":"\u0431\u0430\u0439\u0434\u0430\u043b","r":"baidal","s":0.1556},"sunny":{"f":"\u043d\u0430\u0440\u043b\u0430\u0433","r":"narlag","s":0.1556},"ulcer":{"f":"\u0448\u0430\u0440\u0445","r":"sharkh","s":0.1556},"delicious":{"f":"\u0433\u0430\u0439\u0445\u0430\u043c\u0448\u0438\u0433\u0442\u0430\u0439","r":"gaikhamshigtai","s":0.1548},"condition":{"f":"\u0431\u0430\u0439\u0434\u0430\u043b","r":"baidal","s":0.1546},"newspaper":{"f":"\u0441\u043e\u043d\u0438\u043d","r":"sonin","s":0.1546},"diarrhea":{"f":"\u0441\u0443\u0443\u043b\u0433\u0430\u043b\u0442","r":"suulgalt","s":0.1542},"consciousness":{"f":"\u0443\u0445\u0430\u043c\u0441\u0430\u0440","r":"ukhamsar","s":0.154},"robber":{"f":"\u0434\u044d\u044d\u0440\u044d\u043c\u0447\u0438\u043d","r":"deeremchin","s":0.1538},"nettle":{"f":"\u0445\u0430\u043b\u0433\u0430\u0439","r":"khalgai","s":0.152},"oyster":{"f":"\u0445\u044f\u0441\u0430\u0430","r":"khiasaa","s":0.152},"saffron":{"f":"\u0433\u04af\u0440\u0433\u044d\u043c","r":"gurgem","s":0.152},"vector":{"f":"\u0447\u0438\u0433\u043b\u044d\u043b","r":"chiglel","s":0.152},"myriad":{"f":"\u0442\u04af\u043c","r":"tum","s":0.15},"pig":{"f":"\u0433\u0430\u0445\u0430\u0439","r":"gakhai","s":0.15},"magazine":{"f":"\u0441\u044d\u0442\u0433\u04af\u04af\u043b","r":"setguul","s":0.1494},"perhaps":{"f":"\u043c\u0430\u0433\u0430\u0434\u0433\u04af\u0439","r":"magadgui","s":0.1494},"historical":{"f":"\u0442\u04af\u04af\u0445\u044d\u043d","r":"tuukhen","s":0.1471},"method":{"f":"\u0445\u044d\u0440\u044d\u0433\u043b\u04af\u04af\u0440","r":"kheregluur","s":0.1461},"post":{"f":"\u0448\u0443\u0443\u0434\u0430\u043d","r":"shuudan","s":0.1446},"surname":{"f":"\u1823\u182a\u1824\u182d","r":"obug","s":0.1446},"stack":{"f":"\u0431\u0443\u0445\u0430\u043b","r":"bukhal","s":0.1444},"pronounce":{"f":"\u0434\u0443\u0443\u0434\u0430\u0445","r":"duudakh","s":0.1434},"conscience":{"f":"\u0443\u0445\u0430\u043c\u0441\u0430\u0440","r":"ukhamsar","s":0.1421},"prosecutor":{"f":"\u044f\u043b\u043b\u0430\u0433\u0447","r":"iallagch","s":0.1421},"jupiter":{"f":"\u0431\u0430\u0440\u0445\u0430\u0441\u0431\u0430\u0434\u044c","r":"barkhasbad","s":0.1386},"new":{"f":"\u1830\u1822\u1828\u180e\u1821","r":"sine","s":0.1375},"major":{"f":"\u0445\u043e\u0448\u0443\u0443\u0447","r":"khoshuuch","s":0.137},"ruby":{"f":"\u0431\u0430\u0434\u043c\u0430\u0430\u0440\u0430\u0433","r":"badmaarag","s":0.1356},"elector":{"f":"\u0441\u043e\u043d\u0433\u043e\u0433\u0447","r":"songogch","s":0.1301},"like":{"f":"\u0434\u0443\u0440\u043b\u0430\u0445","r":"durlakh","s":0.1143},"do":{"f":"\u0443\u0443","r":"uu","s":0.1},"nut":{"f":"\u1830\u1820\u182e\u1824\u1837","r":"samur","s":0.09},"tiger":{"f":"\u0431\u0430\u0440","r":"bar","s":0.09},"center":{"f":"\u0442\u04e9\u0432","r":"tov","s":0.075},"head":{"f":"\u1832\u1823\u182f\u1824\u182d\u1820\u1822","r":"tolugai","s":0.0714},"live":{"f":"\u043e\u0440\u0448\u0438\u0445","r":"orshikh","s":0.0714},"coconut":{"f":"\u0431\u044d\u0442","r":"bet","s":0.0643},"cannabis":{"f":"\u043e\u043b\u0441","r":"ols","s":0.0563},"win":{"f":"\u0445\u043e\u0436\u0438\u0445","r":"khozhikh","s":0.0563},"real":{"f":"\u0436\u0438\u043d\u0445\u044d\u043d\u044d","r":"zhinkhene","s":0.0556},"tool":{"f":"\u0445\u044d\u0440\u044d\u0433\u0441\u044d\u043b","r":"kheregsel","s":0.0556},"work":{"f":"\u0430\u0436\u0438\u043b\u043b\u0430\u0445","r":"azhillakh","s":0.0556},"-er":{"f":"-\u0433\u0447","r":"gch","s":0.05},"age":{"f":"\u043d\u0430\u0441","r":"nas","s":0.05},"bad":{"f":"\u043c\u0443\u0443","r":"muu","s":0.05},"bed":{"f":"\u1823\u1837\u1823","r":"oro","s":0.05},"bone":{"f":"\u1836\u180b\u1820\u1830\u1824","r":"yasu","s":0.05},"cat":{"f":"\u043c\u0438\u0439","r":"mii","s":0.05},"cedar":{"f":"\u0445\u0443\u0448","r":"khush","s":0.05},"death":{"f":"\u04af\u0445\u044d\u043b","r":"ukhel","s":0.05},"deer":{"f":"\u0431\u0443\u0433\u0430","r":"buga","s":0.05},"fat":{"f":"\u0442\u043e\u0441","r":"tos","s":0.05},"fence":{"f":"\u0445\u0430\u0439\u0441","r":"khais","s":0.05},"furnace":{"f":"\u043f\u0438\u0439\u0448\u0438\u043d","r":"piishin","s":0.05},"gas":{"f":"\u182c\u1821\u1822","r":"qei","s":0.05},"genus":{"f":"\u0442\u04e9\u0440\u04e9\u043b","r":"torol","s":0.05},"leg":{"f":"\u182c\u1825\u182f","r":"qol","s":0.05},"letter":{"f":"\u0437\u0430\u0445\u0438\u0430","r":"zakhia","s":0.05},"murder":{"f":"\u0430\u043b\u043b\u0430\u0433\u0430","r":"allaga","s":0.05},"paint":{"f":"\u0431\u0443\u0434\u0430\u0433","r":"budag","s":0.05},"pair":{"f":"\u0445\u043e\u0441","r":"khos","s":0.05},"pawn":{"f":"\u0445\u04af\u04af","r":"khuu","s":0.05},"pearl":{"f":"\u1830\u1824\u182a\u1824\u1833","r":"subud","s":0.05},"she":{"f":"\u0442\u044d\u0440","r":"ter","s":0.05},"shit":{"f":"\u0431\u0430\u0430\u0441","r":"baas","s":0.05},"son":{"f":"\u182c\u1826\u1826","r":"quu","s":0.05},"usa":{"f":"\u0430\u043d\u0443","r":"anu","s":0.05},"west":{"f":"\u04e9\u0440\u043d\u04e9","r":"orno","s":0.05},"wine":{"f":"\u0434\u0430\u0440\u0441","r":"dars","s":0.05},"year":{"f":"\u0436\u0438\u043b","r":"zhil","s":0.05},"ill":{"f":"\u1825\u182a\u1821\u1833\u1834\u1822\u1832\u1821\u1822","r":"obedchitei","s":0.045},"dormouse":{"f":"\u0443\u043d\u0442\u0430\u0430\u0445\u0430\u0439","r":"untaakhai","s":0.0444},"metaphor":{"f":"\u0437\u04af\u0439\u0440\u043b\u044d\u043b","r":"zuirlel","s":0.0438},"police":{"f":"\u0446\u0430\u0433\u0434\u0430\u0430","r":"tsagdaa","s":0.0429},"sesame":{"f":"\u0433\u04af\u043d\u0436\u0438\u0434","r":"gunzhid","s":0.0429},"vagina":{"f":"\u1826\u1832\u1826\u1837\u1826\u182d\u1821","r":"uturuge","s":0.0429},"brass":{"f":"\u0433\u0443\u0443\u043b\u0438\u043d","r":"guulin","s":0.0417},"butter":{"f":"\u043c\u0430\u0441\u043b\u043e","r":"maslo","s":0.0417},"climb":{"f":"\u04e9\u0433\u0441\u04e9\u0445","r":"ogsokh","s":0.0417},"close":{"f":"\u0445\u0430\u0430\u0445","r":"khaakh","s":0.0417},"height":{"f":"\u04e9\u043d\u0434\u04e9\u0440","r":"ondor","s":0.0417},"inside":{"f":"\u0434\u043e\u0442\u043e\u0440","r":"dotor","s":0.0417},"otter":{"f":"\u0445\u0430\u043b\u0438\u0433","r":"khalig","s":0.0417},"silver":{"f":"\u043c\u04e9\u043d\u0433\u04e9","r":"mongo","s":0.0417},"steer":{"f":"\u0437\u0430\u043b\u0430\u0445","r":"zalakh","s":0.0417},"stone":{"f":"\u0447\u0443\u043b\u0443\u0443","r":"chuluu","s":0.0417},"torch":{"f":"\u0431\u0430\u043c\u0431\u0430\u0440","r":"bambar","s":0.0417},"back":{"f":"\u043d\u0443\u0440\u0443\u0443","r":"nuruu","s":0.04},"burn":{"f":"\u0430\u0441\u0430\u0445","r":"asakh","s":0.04},"butt":{"f":"\u04e9\u0433\u0437\u04e9\u0433","r":"ogzog","s":0.04},"coal":{"f":"\u043d\u04af\u04af\u0440\u0441","r":"nuurs","s":0.04},"earn":{"f":"\u043e\u043b\u043e\u0445","r":"olokh","s":0.04},"lamp":{"f":"\u0433\u044d\u0440\u044d\u043b","r":"gerel","s":0.04},"love":{"f":"\u0445\u0430\u0439\u0440","r":"khair","s":0.04},"myth":{"f":"\u0434\u043e\u043c\u043e\u0433","r":"domog","s":0.04},"pipe":{"f":"\u0442\u0440\u0443\u0431\u0430","r":"truba","s":0.04},"sand":{"f":"\u1821\u182f\u1821\u1830\u1826","r":"elesu","s":0.04},"sense":{"f":"\u0443\u0442\u0433\u0430","r":"utga","s":0.04},"silk":{"f":"\u0442\u043e\u0440\u0433\u043e","r":"torgo","s":0.04},"skin":{"f":"\u1820\u1837\u1820\u1830\u1824","r":"arasu","s":0.04},"slave":{"f":"\u0431\u043e\u043e\u043b","r":"bool","s":0.04},"tyre":{"f":"\u0434\u0443\u0433\u0443\u0439","r":"dugui","s":0.04},"vote":{"f":"\u0441\u0430\u043d\u0430\u043b","r":"sanal","s":0.04},"week":{"f":"\u0433\u0430\u0440\u0438\u0433","r":"garig","s":0.04},"bye":{"f":"\u043f\u043e\u043a\u0430","r":"poka","s":0.0375},"condom":{"f":"\u0431\u044d\u043b\u0433\u044d\u0432\u0447","r":"belgevch","s":0.0375},"cow":{"f":"\u04af\u043d\u044d\u044d","r":"unee","s":0.0375},"deep":{"f":"\u0433\u04af\u043d","r":"gun","s":0.0375},"fire":{"f":"\u0433\u0430\u043b","r":"gal","s":0.0375},"fox":{"f":"\u04af\u043d\u044d\u0433","r":"uneg","s":0.0375},"knob":{"f":"\u0438\u0448","r":"ish","s":0.0375},"long":{"f":"\u0443\u0440\u0442","r":"urt","s":0.0375},"lot":{"f":"\u0445\u0443\u0432\u044c","r":"khuv","s":0.0375},"mammal":{"f":"\u0445\u04e9\u0445\u0442\u04e9\u043d","r":"khokhton","s":0.0375},"milk":{"f":"\u0441\u04af\u04af","r":"suu","s":0.0375},"our":{"f":"\u043c\u0430\u0430\u043d\u044c","r":"maan","s":0.0375},"star":{"f":"\u1823\u1833\u180b\u1824","r":"odu","s":0.0375},"this":{"f":"\u044d\u043d\u044d","r":"ene","s":0.0375},"word":{"f":"\u1826\u182d\u1821","r":"uge","s":0.0375},"yes":{"f":"\u0442\u0438\u0439\u043c","r":"tiim","s":0.0375},"alcohol":{"f":"\u0441\u043f\u0438\u0440\u0442","r":"spirt","s":0.0357},"giddy":{"f":"\u0445\u04e9\u043d\u0433\u04e9\u043d","r":"khongon","s":0.0357},"gourd":{"f":"\u0448\u0438\u0439\u0433\u0443\u0430","r":"shiigua","s":0.0357},"shoot":{"f":"\u0431\u0443\u0443\u0434\u0430\u0445","r":"buudakh","s":0.0357},"small":{"f":"\u0436\u0438\u0436\u0438\u0433","r":"zhizhig","s":0.0357},"and":{"f":"\u0431\u0430","r":"ba","s":0.0333},"dead":{"f":"\u04af\u0445\u0441\u044d\u043d","r":"ukhsen","s":0.0333},"flow":{"f":"\u0443\u0440\u0441\u0433\u0430\u043b","r":"ursgal","s":0.0333},"if":{"f":"-\u0431\u0430\u043b","r":"bal","s":0.0333},"life":{"f":"\u0430\u043c\u044c\u0434\u0440\u0430\u043b","r":"amdral","s":0.0333},"line":{"f":"\u0448\u0443\u0433\u0430\u043c","r":"shugam","s":0.0333},"loud":{"f":"\u0447\u0430\u043d\u0433\u0430","r":"changa","s":0.0333},"sign":{"f":"\u0442\u044d\u043c\u0434\u044d\u0433","r":"temdeg","s":0.0333},"sister":{"f":"\u044d\u0433\u0447","r":"egch","s":0.0333},"spoilt":{"f":"\u044d\u0440\u0445","r":"erkh","s":0.0333},"tour":{"f":"\u0430\u044f\u043b\u0430\u043b","r":"aialal","s":0.0333},"we":{"f":"\u0431\u0438\u0434","r":"bid","s":0.0333},"wear":{"f":"\u04e9\u043c\u0441\u04e9\u0445","r":"omsokh","s":0.0333},"hedgehog":{"f":"\u0437\u0430\u0440\u0430\u0430","r":"zaraa","s":0.0312},"ban":{"f":"\u0446\u044d\u044d\u0440","r":"tseer","s":0.03},"buy":{"f":"\u0430\u0432\u0430\u0445","r":"avakh","s":0.03},"ear":{"f":"\u0447\u0438\u0445","r":"chikh","s":0.03},"how":{"f":"\u044f\u0430\u0436","r":"iaazh","s":0.03},"red":{"f":"\u0443\u043b\u0430\u0430\u043d","r":"ulaan","s":0.03},"refuse":{"f":"\u0442\u0430\u0442\u0433\u0430\u043b\u0437\u0430\u0445","r":"tatgalzakh","s":0.03},"stick":{"f":"\u043c\u043e\u0434","r":"mod","s":0.03},"tip":{"f":"\u04af\u0437\u04af\u04af\u0440","r":"uzuur","s":0.03},"water":{"f":"\u1824\u1830\u1824","r":"usu","s":0.03},"fast":{"f":"\u0445\u0443\u0440\u0434\u0430\u043d","r":"khurdan","s":0.0286},"lame":{"f":"\u0434\u043e\u0433\u043e\u043b\u043e\u043d","r":"dogolon","s":0.0286},"mustard":{"f":"\u0433\u0438\u0447","r":"gich","s":0.0286},"read":{"f":"\u0443\u043d\u0448\u0438\u0445","r":"unshikh","s":0.0286},"tube":{"f":"\u0445\u043e\u043e\u043b\u043e\u0439","r":"khooloi","s":0.0286},"dryer":{"f":"\u0445\u0430\u0442\u0430\u0430\u0433\u0447","r":"khataagch","s":0.0278},"dragon":{"f":"\u043b\u0443\u0443","r":"luu","s":0.025},"fin":{"f":"\u0441\u044d\u0440\u0432\u044d\u044d","r":"servee","s":0.025},"fix":{"f":"\u0437\u0430\u0441\u0430\u0445","r":"zasakh","s":0.025},"god":{"f":"\u182a\u1824\u1837\u182c\u1820\u1828","r":"burqan","s":0.025},"luck":{"f":"\u0430\u0437","r":"az","s":0.025},"no":{"f":"\u04af\u0433\u04af\u0439","r":"ugui","s":0.025},"saw":{"f":"\u0445\u04e9\u0440\u04e9\u04e9","r":"khoroo","s":0.025},"mow":{"f":"\u0445\u0430\u0434\u0430\u0445","r":"khadakh","s":0.0214},"raw":{"f":"\u0442\u04af\u04af\u0445\u0438\u0439","r":"tuukhii","s":0.0214},"why":{"f":"\u044f\u0430\u0433\u0430\u0430\u0434","r":"iaagaad","s":0.0214},"blade":{"f":"\u0438\u0440","r":"ir","s":0.02},"ox":{"f":"\u04af\u0445\u044d\u0440","r":"ukher","s":0.02},"dry":{"f":"\u0445\u0430\u0442\u0430\u0430\u0445","r":"khataakh","s":0.0188}}