{"info": {"lang": "Russian", "n": 10000, "avg": 0.35589615581882617, "high_pct": 14.59, "mid_pct": 16.3, "low_pct": 69.11, "code": "ru", "family": "Slavic"}, "identical_count": 753, "identical_sample": [{"en": "for", "foreign": "for", "rom": "for", "score": 1.0, "lev": 1.0, "jw": 1.0, "meta": 1.0, "sound": 1.0, "bi": 1.0, "tri": 1.0}, {"en": "that", "foreign": "that", "rom": "that", "score": 1.0, "lev": 1.0, "jw": 1.0, "meta": 1.0, "sound": 1.0, "bi": 1.0, "tri": 1.0}, {"en": "with", "foreign": "with", "rom": "with", "score": 1.0, "lev": 1.0, "jw": 1.0, "meta": 1.0, "sound": 1.0, "bi": 1.0, "tri": 1.0}, {"en": "from", "foreign": "from", "rom": "from", "score": 1.0, "lev": 1.0, "jw": 1.0, "meta": 1.0, "sound": 1.0, "bi": 1.0, "tri": 1.0}, {"en": "this", "foreign": "this", "rom": "this", "score": 1.0, "lev": 1.0, "jw": 1.0, "meta": 1.0, "sound": 1.0, "bi": 1.0, "tri": 1.0}, {"en": "utc", "foreign": "utc", "rom": "utc", "score": 1.0, "lev": 1.0, "jw": 1.0, "meta": 1.0, "sound": 1.0, "bi": 1.0, "tri": 1.0}, {"en": "one", "foreign": "one", "rom": "one", "score": 1.0, "lev": 1.0, "jw": 1.0, "meta": 1.0, "sound": 1.0, "bi": 1.0, "tri": 1.0}, {"en": "first", "foreign": "first", "rom": "first", "score": 1.0, "lev": 1.0, "jw": 1.0, "meta": 1.0, "sound": 1.0, "bi": 1.0, "tri": 1.0}, {"en": "page", "foreign": "page", "rom": "page", "score": 1.0, "lev": 1.0, "jw": 1.0, "meta": 1.0, "sound": 1.0, "bi": 1.0, "tri": 1.0}, {"en": "you", "foreign": "you", "rom": "you", "score": 1.0, "lev": 1.0, "jw": 1.0, "meta": 1.0, "sound": 1.0, "bi": 1.0, "tri": 1.0}, {"en": "who", "foreign": "who", "rom": "who", "score": 1.0, "lev": 1.0, "jw": 1.0, "meta": 1.0, "sound": 1.0, "bi": 1.0, "tri": 1.0}, {"en": "all", "foreign": "all", "rom": "all", "score": 1.0, "lev": 1.0, "jw": 1.0, "meta": 1.0, "sound": 1.0, "bi": 1.0, "tri": 1.0}, {"en": "after", "foreign": "after", "rom": "after", "score": 1.0, "lev": 1.0, "jw": 1.0, "meta": 1.0, "sound": 1.0, "bi": 1.0, "tri": 1.0}, {"en": "can", "foreign": "can", "rom": "can", "score": 1.0, "lev": 1.0, "jw": 1.0, "meta": 1.0, "sound": 1.0, "bi": 1.0, "tri": 1.0}, {"en": "she", "foreign": "she", "rom": "she", "score": 1.0, "lev": 1.0, "jw": 1.0, "meta": 1.0, "sound": 1.0, "bi": 1.0, "tri": 1.0}, {"en": "about", "foreign": "about", "rom": "about", "score": 1.0, "lev": 1.0, "jw": 1.0, "meta": 1.0, "sound": 1.0, "bi": 1.0, "tri": 1.0}, {"en": "when", "foreign": "when", "rom": "when", "score": 1.0, "lev": 1.0, "jw": 1.0, "meta": 1.0, "sound": 1.0, "bi": 1.0, "tri": 1.0}, {"en": "time", "foreign": "time", "rom": "time", "score": 1.0, "lev": 1.0, "jw": 1.0, "meta": 1.0, "sound": 1.0, "bi": 1.0, "tri": 1.0}, {"en": "team", "foreign": "team", "rom": "team", "score": 1.0, "lev": 1.0, "jw": 1.0, "meta": 1.0, "sound": 1.0, "bi": 1.0, "tri": 1.0}, {"en": "american", "foreign": "american", "rom": "american", "score": 1.0, "lev": 1.0, "jw": 1.0, "meta": 1.0, "sound": 1.0, "bi": 1.0, "tri": 1.0}], "top_cognates": [{"en": "administrator", "foreign": "\u0430\u0434\u043c\u0438\u043d\u0438\u0441\u0442\u0440\u0430\u0442\u043e\u0440\u0430", "rom": "administratora", "score": 0.9673, "lev": 0.929, "jw": 0.986, "meta": 1.0, "sound": 1.0, "bi": 1.0, "tri": 0.917}, {"en": "massachusetts", "foreign": "\u043c\u0430\u0441\u0441\u0430\u0447\u0443\u0441\u0435\u0442\u0441", "rom": "massachusets", "score": 0.9484, "lev": 0.923, "jw": 0.985, "meta": 1.0, "sound": 1.0, "bi": 0.917, "tri": 0.75}, {"en": "monitoring", "foreign": "\u043c\u043e\u043d\u0438\u0442\u043e\u0440\u0438\u043d\u0433\u0430", "rom": "monitoringa", "score": 0.9481, "lev": 0.909, "jw": 0.982, "meta": 1.0, "sound": 1.0, "bi": 0.9, "tri": 0.889}, {"en": "temperature", "foreign": "\u0442\u0435\u043c\u043f\u0435\u0440\u0430\u0442\u0443\u0440\u0430", "rom": "temperatura", "score": 0.9436, "lev": 0.909, "jw": 0.964, "meta": 1.0, "sound": 1.0, "bi": 0.9, "tri": 0.8}, {"en": "marketing", "foreign": "\u043c\u0430\u0440\u043a\u0435\u0442\u0438\u043d\u0433\u0430", "rom": "marketinga", "score": 0.9426, "lev": 0.9, "jw": 0.98, "meta": 1.0, "sound": 1.0, "bi": 0.889, "tri": 0.875}, {"en": "literature", "foreign": "\u043b\u0438\u0442\u0435\u0440\u0430\u0442\u0443\u0440\u0430", "rom": "literatura", "score": 0.9378, "lev": 0.9, "jw": 0.96, "meta": 1.0, "sound": 1.0, "bi": 0.889, "tri": 0.778}, {"en": "institute", "foreign": "\u0438\u043d\u0441\u0442\u0438\u0442\u0443\u0442", "rom": "institut", "score": 0.9359, "lev": 0.889, "jw": 0.978, "meta": 1.0, "sound": 1.0, "bi": 0.875, "tri": 0.857}, {"en": "material", "foreign": "\u043c\u0430\u0442\u0435\u0440\u0438\u0430\u043b\u044b", "rom": "materialy", "score": 0.9359, "lev": 0.889, "jw": 0.978, "meta": 1.0, "sound": 1.0, "bi": 0.875, "tri": 0.857}, {"en": "pakistan", "foreign": "\u043f\u0430\u043a\u0438\u0441\u0442\u0430\u043d\u0430", "rom": "pakistana", "score": 0.9359, "lev": 0.889, "jw": 0.978, "meta": 1.0, "sound": 1.0, "bi": 0.875, "tri": 0.857}, {"en": "argument", "foreign": "\u0430\u0440\u0433\u0443\u043c\u0435\u043d\u0442\u044b", "rom": "argumenty", "score": 0.9359, "lev": 0.889, "jw": 0.978, "meta": 1.0, "sound": 1.0, "bi": 0.875, "tri": 0.857}, {"en": "platform", "foreign": "\u043f\u043b\u0430\u0442\u0444\u043e\u0440\u043c\u0443", "rom": "platformu", "score": 0.9359, "lev": 0.889, "jw": 0.978, "meta": 1.0, "sound": 1.0, "bi": 0.875, "tri": 0.857}, {"en": "platform", "foreign": "\u043f\u043b\u0430\u0442\u0444\u043e\u0440\u043c\u044b", "rom": "platformy", "score": 0.9359, "lev": 0.889, "jw": 0.978, "meta": 1.0, "sound": 1.0, "bi": 0.875, "tri": 0.857}, {"en": "platform", "foreign": "\u043f\u043b\u0430\u0442\u0444\u043e\u0440\u043c\u0430", "rom": "platforma", "score": 0.9359, "lev": 0.889, "jw": 0.978, "meta": 1.0, "sound": 1.0, "bi": 0.875, "tri": 0.857}, {"en": "baltimore", "foreign": "\u0431\u0430\u043b\u0442\u0438\u043c\u043e\u0440", "rom": "baltimor", "score": 0.9359, "lev": 0.889, "jw": 0.978, "meta": 1.0, "sound": 1.0, "bi": 0.875, "tri": 0.857}, {"en": "alternative", "foreign": "\u0430\u043b\u044c\u0442\u0435\u0440\u043d\u0430\u0442\u0438\u0432\u0430", "rom": "alternativa", "score": 0.9355, "lev": 0.909, "jw": 0.964, "meta": 1.0, "sound": 1.0, "bi": 0.818, "tri": 0.8}, {"en": "temperature", "foreign": "\u0442\u0435\u043c\u043f\u0435\u0440\u0430\u0442\u0443\u0440\u044b", "rom": "temperatury", "score": 0.9355, "lev": 0.909, "jw": 0.964, "meta": 1.0, "sound": 1.0, "bi": 0.818, "tri": 0.8}, {"en": "temperature", "foreign": "\u0442\u0435\u043c\u043f\u0435\u0440\u0430\u0442\u0443\u0440\u0443", "rom": "temperaturu", "score": 0.9355, "lev": 0.909, "jw": 0.964, "meta": 1.0, "sound": 1.0, "bi": 0.818, "tri": 0.8}, {"en": "montgomery", "foreign": "\u043c\u043e\u043d\u0442\u0433\u043e\u043c\u0435\u0440\u0438", "rom": "montgomeri", "score": 0.9289, "lev": 0.9, "jw": 0.96, "meta": 1.0, "sound": 1.0, "bi": 0.8, "tri": 0.778}, {"en": "million", "foreign": "\u043c\u0438\u043b\u043b\u0438\u043e\u043d\u0430", "rom": "milliona", "score": 0.9274, "lev": 0.875, "jw": 0.975, "meta": 1.0, "sound": 1.0, "bi": 0.857, "tri": 0.833}, {"en": "problem", "foreign": "\u043f\u0440\u043e\u0431\u043b\u0435\u043c\u044b", "rom": "problemy", "score": 0.9274, "lev": 0.875, "jw": 0.975, "meta": 1.0, "sound": 1.0, "bi": 0.857, "tri": 0.833}, {"en": "problem", "foreign": "\u043f\u0440\u043e\u0431\u043b\u0435\u043c\u0430", "rom": "problema", "score": 0.9274, "lev": 0.875, "jw": 0.975, "meta": 1.0, "sound": 1.0, "bi": 0.857, "tri": 0.833}, {"en": "senator", "foreign": "\u0441\u0435\u043d\u0430\u0442\u043e\u0440\u0430", "rom": "senatora", "score": 0.9274, "lev": 0.875, "jw": 0.975, "meta": 1.0, "sound": 1.0, "bi": 0.857, "tri": 0.833}, {"en": "marshall", "foreign": "\u043c\u0430\u0440\u0448\u0430\u043b", "rom": "marshal", "score": 0.9274, "lev": 0.875, "jw": 0.975, "meta": 1.0, "sound": 1.0, "bi": 0.857, "tri": 0.833}, {"en": "mitchell", "foreign": "\u043c\u0438\u0442\u0447\u0435\u043b", "rom": "mitchel", "score": 0.9274, "lev": 0.875, "jw": 0.975, "meta": 1.0, "sound": 1.0, "bi": 0.857, "tri": 0.833}, {"en": "segment", "foreign": "\u0441\u0435\u0433\u043c\u0435\u043d\u0442\u0430", "rom": "segmenta", "score": 0.9274, "lev": 0.875, "jw": 0.975, "meta": 1.0, "sound": 1.0, "bi": 0.857, "tri": 0.833}, {"en": "protest", "foreign": "\u043f\u0440\u043e\u0442\u0435\u0441\u0442\u0430", "rom": "protesta", "score": 0.9274, "lev": 0.875, "jw": 0.975, "meta": 1.0, "sound": 1.0, "bi": 0.857, "tri": 0.833}, {"en": "protest", "foreign": "\u043f\u0440\u043e\u0442\u0435\u0441\u0442\u044b", "rom": "protesty", "score": 0.9274, "lev": 0.875, "jw": 0.975, "meta": 1.0, "sound": 1.0, "bi": 0.857, "tri": 0.833}, {"en": "uniform", "foreign": "\u0443\u043d\u0438\u0444\u043e\u0440\u043c\u0430", "rom": "uniforma", "score": 0.9274, "lev": 0.875, "jw": 0.975, "meta": 1.0, "sound": 1.0, "bi": 0.857, "tri": 0.833}, {"en": "adelaide", "foreign": "\u0430\u0434\u0435\u043b\u0430\u0438\u0434\u0430", "rom": "adelaida", "score": 0.9214, "lev": 0.875, "jw": 0.95, "meta": 1.0, "sound": 1.0, "bi": 0.857, "tri": 0.714}, {"en": "minnesota", "foreign": "\u043c\u0438\u043d\u043d\u0435\u0441\u043e\u0442\u044b", "rom": "minnesoty", "score": 0.9208, "lev": 0.889, "jw": 0.956, "meta": 1.0, "sound": 1.0, "bi": 0.778, "tri": 0.75}, {"en": "programme", "foreign": "\u043f\u0440\u043e\u0433\u0440\u0430\u043c\u043c\u0430", "rom": "programma", "score": 0.9208, "lev": 0.889, "jw": 0.956, "meta": 1.0, "sound": 1.0, "bi": 0.778, "tri": 0.75}, {"en": "argentine", "foreign": "\u0430\u0440\u0433\u0435\u043d\u0442\u0438\u043d\u044b", "rom": "argentiny", "score": 0.9208, "lev": 0.889, "jw": 0.956, "meta": 1.0, "sound": 1.0, "bi": 0.778, "tri": 0.75}, {"en": "pakistani", "foreign": "\u043f\u0430\u043a\u0438\u0441\u0442\u0430\u043d\u0430", "rom": "pakistana", "score": 0.9208, "lev": 0.889, "jw": 0.956, "meta": 1.0, "sound": 1.0, "bi": 0.778, "tri": 0.75}, {"en": "palestine", "foreign": "\u043f\u0430\u043b\u0435\u0441\u0442\u0438\u043d\u044b", "rom": "palestiny", "score": 0.9208, "lev": 0.889, "jw": 0.956, "meta": 1.0, "sound": 1.0, "bi": 0.778, "tri": 0.75}, {"en": "palestine", "foreign": "\u043f\u0430\u043b\u0435\u0441\u0442\u0438\u043d\u0443", "rom": "palestinu", "score": 0.9208, "lev": 0.889, "jw": 0.956, "meta": 1.0, "sound": 1.0, "bi": 0.778, "tri": 0.75}, {"en": "palestine", "foreign": "\u043f\u0430\u043b\u0435\u0441\u0442\u0438\u043d\u0430", "rom": "palestina", "score": 0.9208, "lev": 0.889, "jw": 0.956, "meta": 1.0, "sound": 1.0, "bi": 0.778, "tri": 0.75}, {"en": "metropolitan", "foreign": "\u043c\u0435\u0442\u0440\u043e\u043f\u043e\u043b\u0438\u0442\u0435\u043d", "rom": "metropoliten", "score": 0.9192, "lev": 0.917, "jw": 0.967, "meta": 1.0, "sound": 1.0, "bi": 0.692, "tri": 0.667}, {"en": "profile", "foreign": "\u043f\u0440\u043e\u0444\u0438\u043b\u044c", "rom": "profil", "score": 0.9162, "lev": 0.857, "jw": 0.971, "meta": 1.0, "sound": 1.0, "bi": 0.833, "tri": 0.8}, {"en": "gordon", "foreign": "\u0433\u043e\u0440\u0434\u043e\u043d\u0430", "rom": "gordona", "score": 0.9162, "lev": 0.857, "jw": 0.971, "meta": 1.0, "sound": 1.0, "bi": 0.833, "tri": 0.8}, {"en": "planet", "foreign": "\u043f\u043b\u0430\u043d\u0435\u0442\u0435", "rom": "planete", "score": 0.9162, "lev": 0.857, "jw": 0.971, "meta": 1.0, "sound": 1.0, "bi": 0.833, "tri": 0.8}, {"en": "planet", "foreign": "\u043f\u043b\u0430\u043d\u0435\u0442\u0430", "rom": "planeta", "score": 0.9162, "lev": 0.857, "jw": 0.971, "meta": 1.0, "sound": 1.0, "bi": 0.833, "tri": 0.8}, {"en": "legend", "foreign": "\u043b\u0435\u0433\u0435\u043d\u0434\u044b", "rom": "legendy", "score": 0.9162, "lev": 0.857, "jw": 0.971, "meta": 1.0, "sound": 1.0, "bi": 0.833, "tri": 0.8}, {"en": "legend", "foreign": "\u043b\u0435\u0433\u0435\u043d\u0434\u0430", "rom": "legenda", "score": 0.9162, "lev": 0.857, "jw": 0.971, "meta": 1.0, "sound": 1.0, "bi": 0.833, "tri": 0.8}, {"en": "reform", "foreign": "\u0440\u0435\u0444\u043e\u0440\u043c\u044b", "rom": "reformy", "score": 0.9162, "lev": 0.857, "jw": 0.971, "meta": 1.0, "sound": 1.0, "bi": 0.833, "tri": 0.8}, {"en": "reform", "foreign": "\u0440\u0435\u0444\u043e\u0440\u043c\u0430", "rom": "reforma", "score": 0.9162, "lev": 0.857, "jw": 0.971, "meta": 1.0, "sound": 1.0, "bi": 0.833, "tri": 0.8}, {"en": "dublin", "foreign": "\u0434\u0443\u0431\u043b\u0438\u043d\u0435", "rom": "dubline", "score": 0.9162, "lev": 0.857, "jw": 0.971, "meta": 1.0, "sound": 1.0, "bi": 0.833, "tri": 0.8}, {"en": "morgan", "foreign": "\u043c\u043e\u0440\u0433\u0430\u043d\u0430", "rom": "morgana", "score": 0.9162, "lev": 0.857, "jw": 0.971, "meta": 1.0, "sound": 1.0, "bi": 0.833, "tri": 0.8}, {"en": "charlie", "foreign": "\u0447\u0430\u0440\u043b\u0438", "rom": "charli", "score": 0.9162, "lev": 0.857, "jw": 0.971, "meta": 1.0, "sound": 1.0, "bi": 0.833, "tri": 0.8}, {"en": "madrid", "foreign": "\u043c\u0430\u0434\u0440\u0438\u0434\u0435", "rom": "madride", "score": 0.9162, "lev": 0.857, "jw": 0.971, "meta": 1.0, "sound": 1.0, "bi": 0.833, "tri": 0.8}, {"en": "oliver", "foreign": "\u043e\u043b\u0438\u0432\u0435\u0440\u0430", "rom": "olivera", "score": 0.9162, "lev": 0.857, "jw": 0.971, "meta": 1.0, "sound": 1.0, "bi": 0.833, "tri": 0.8}, {"en": "patent", "foreign": "\u043f\u0430\u0442\u0435\u043d\u0442\u0430", "rom": "patenta", "score": 0.9162, "lev": 0.857, "jw": 0.971, "meta": 1.0, "sound": 1.0, "bi": 0.833, "tri": 0.8}, {"en": "sheriff", "foreign": "\u0448\u0435\u0440\u0438\u0444", "rom": "sherif", "score": 0.9162, "lev": 0.857, "jw": 0.971, "meta": 1.0, "sound": 1.0, "bi": 0.833, "tri": 0.8}, {"en": "nigeria", "foreign": "\u043d\u0438\u0433\u0435\u0440\u0438\u044f", "rom": "nigeriia", "score": 0.9143, "lev": 0.875, "jw": 0.975, "meta": 1.0, "sound": 1.0, "bi": 0.857, "tri": 0.571}, {"en": "department", "foreign": "\u0434\u0435\u043f\u0430\u0440\u0442\u0430\u043c\u0435\u043d\u0442", "rom": "departament", "score": 0.9136, "lev": 0.909, "jw": 0.982, "meta": 1.0, "sound": 1.0, "bi": 0.727, "tri": 0.545}, {"en": "london", "foreign": "\u043b\u043e\u043d\u0434\u043e\u043d\u0435", "rom": "londone", "score": 0.9129, "lev": 0.857, "jw": 0.971, "meta": 1.0, "sound": 1.0, "bi": 0.8, "tri": 0.8}, {"en": "server", "foreign": "\u0441\u0435\u0440\u0432\u0435\u0440\u0430", "rom": "servera", "score": 0.9129, "lev": 0.857, "jw": 0.971, "meta": 1.0, "sound": 1.0, "bi": 0.8, "tri": 0.8}, {"en": "standard", "foreign": "\u0441\u0442\u0430\u043d\u0434\u0430\u0440\u0442", "rom": "standart", "score": 0.9107, "lev": 0.875, "jw": 0.95, "meta": 1.0, "sound": 1.0, "bi": 0.75, "tri": 0.714}, {"en": "atlantic", "foreign": "\u0430\u0442\u043b\u0430\u043d\u0442\u0438\u043a", "rom": "atlantik", "score": 0.9107, "lev": 0.875, "jw": 0.95, "meta": 1.0, "sound": 1.0, "bi": 0.75, "tri": 0.714}, {"en": "nebraska", "foreign": "\u043d\u0435\u0431\u0440\u0430\u0441\u043a\u0438", "rom": "nebraski", "score": 0.9107, "lev": 0.875, "jw": 0.95, "meta": 1.0, "sound": 1.0, "bi": 0.75, "tri": 0.714}, {"en": "romantic", "foreign": "\u0440\u043e\u043c\u0430\u043d\u0442\u0438\u043a", "rom": "romantik", "score": 0.9107, "lev": 0.875, "jw": 0.95, "meta": 1.0, "sound": 1.0, "bi": 0.75, "tri": 0.714}, {"en": "parliament", "foreign": "\u043f\u0430\u0440\u043b\u0430\u043c\u0435\u043d\u0442", "rom": "parlament", "score": 0.905, "lev": 0.9, "jw": 0.98, "meta": 1.0, "sound": 1.0, "bi": 0.7, "tri": 0.5}, {"en": "frederick", "foreign": "\u0444\u0440\u0435\u0434\u0435\u0440\u0438\u043a", "rom": "frederik", "score": 0.9035, "lev": 0.889, "jw": 0.978, "meta": 1.0, "sound": 1.0, "bi": 0.667, "tri": 0.625}, {"en": "parameter", "foreign": "\u043f\u0430\u0440\u0430\u043c\u0435\u0442\u0440", "rom": "parametr", "score": 0.9035, "lev": 0.889, "jw": 0.978, "meta": 1.0, "sound": 1.0, "bi": 0.667, "tri": 0.625}, {"en": "serbia", "foreign": "\u0441\u0435\u0440\u0431\u0438\u044f", "rom": "serbiia", "score": 0.9012, "lev": 0.857, "jw": 0.971, "meta": 1.0, "sound": 1.0, "bi": 0.833, "tri": 0.5}, {"en": "pioneer", "foreign": "\u043f\u0438\u043e\u043d\u0435\u0440", "rom": "pioner", "score": 0.9012, "lev": 0.857, "jw": 0.971, "meta": 1.0, "sound": 1.0, "bi": 0.833, "tri": 0.5}, {"en": "bosnia", "foreign": "\u0431\u043e\u0441\u043d\u0438\u044f", "rom": "bosniia", "score": 0.9012, "lev": 0.857, "jw": 0.971, "meta": 1.0, "sound": 1.0, "bi": 0.833, "tri": 0.5}, {"en": "single", "foreign": "\u0441\u0438\u043d\u0433\u043b", "rom": "singl", "score": 0.9008, "lev": 0.833, "jw": 0.967, "meta": 1.0, "sound": 1.0, "bi": 0.8, "tri": 0.75}, {"en": "press", "foreign": "\u043f\u0440\u0435\u0441\u0441\u0430", "rom": "pressa", "score": 0.9008, "lev": 0.833, "jw": 0.967, "meta": 1.0, "sound": 1.0, "bi": 0.8, "tri": 0.75}, {"en": "model", "foreign": "\u043c\u043e\u0434\u0435\u043b\u0438", "rom": "modeli", "score": 0.9008, "lev": 0.833, "jw": 0.967, "meta": 1.0, "sound": 1.0, "bi": 0.8, "tri": 0.75}, {"en": "metal", "foreign": "\u043c\u0435\u0442\u0430\u043b\u043b", "rom": "metall", "score": 0.9008, "lev": 0.833, "jw": 0.967, "meta": 1.0, "sound": 1.0, "bi": 0.8, "tri": 0.75}, {"en": "senate", "foreign": "\u0441\u0435\u043d\u0430\u0442", "rom": "senat", "score": 0.9008, "lev": 0.833, "jw": 0.967, "meta": 1.0, "sound": 1.0, "bi": 0.8, "tri": 0.75}, {"en": "forum", "foreign": "\u0444\u043e\u0440\u0443\u043c\u0435", "rom": "forume", "score": 0.9008, "lev": 0.833, "jw": 0.967, "meta": 1.0, "sound": 1.0, "bi": 0.8, "tri": 0.75}, {"en": "angel", "foreign": "\u0430\u043d\u0433\u0435\u043b\u0430", "rom": "angela", "score": 0.9008, "lev": 0.833, "jw": 0.967, "meta": 1.0, "sound": 1.0, "bi": 0.8, "tri": 0.75}, {"en": "panel", "foreign": "\u043f\u0430\u043d\u0435\u043b\u0438", "rom": "paneli", "score": 0.9008, "lev": 0.833, "jw": 0.967, "meta": 1.0, "sound": 1.0, "bi": 0.8, "tri": 0.75}, {"en": "nepal", "foreign": "\u043d\u0435\u043f\u0430\u043b\u0430", "rom": "nepala", "score": 0.9008, "lev": 0.833, "jw": 0.967, "meta": 1.0, "sound": 1.0, "bi": 0.8, "tri": 0.75}, {"en": "nepal", "foreign": "\u043d\u0435\u043f\u0430\u043b\u0435", "rom": "nepale", "score": 0.9008, "lev": 0.833, "jw": 0.967, "meta": 1.0, "sound": 1.0, "bi": 0.8, "tri": 0.75}, {"en": "vegas", "foreign": "\u0432\u0435\u0433\u0430\u0441\u0435", "rom": "vegase", "score": 0.9008, "lev": 0.833, "jw": 0.967, "meta": 1.0, "sound": 1.0, "bi": 0.8, "tri": 0.75}, {"en": "virus", "foreign": "\u0432\u0438\u0440\u0443\u0441\u044b", "rom": "virusy", "score": 0.9008, "lev": 0.833, "jw": 0.967, "meta": 1.0, "sound": 1.0, "bi": 0.8, "tri": 0.75}, {"en": "aaron", "foreign": "\u0430\u0430\u0440\u043e\u043d\u0430", "rom": "aarona", "score": 0.9008, "lev": 0.833, "jw": 0.967, "meta": 1.0, "sound": 1.0, "bi": 0.8, "tri": 0.75}, {"en": "parade", "foreign": "\u043f\u0430\u0440\u0430\u0434", "rom": "parad", "score": 0.9008, "lev": 0.833, "jw": 0.967, "meta": 1.0, "sound": 1.0, "bi": 0.8, "tri": 0.75}, {"en": "aires", "foreign": "\u0430\u0439\u0440\u0435\u0441\u0435", "rom": "airese", "score": 0.9008, "lev": 0.833, "jw": 0.967, "meta": 1.0, "sound": 1.0, "bi": 0.8, "tri": 0.75}, {"en": "orbit", "foreign": "\u043e\u0440\u0431\u0438\u0442\u044b", "rom": "orbity", "score": 0.9008, "lev": 0.833, "jw": 0.967, "meta": 1.0, "sound": 1.0, "bi": 0.8, "tri": 0.75}, {"en": "orbit", "foreign": "\u043e\u0440\u0431\u0438\u0442\u0443", "rom": "orbitu", "score": 0.9008, "lev": 0.833, "jw": 0.967, "meta": 1.0, "sound": 1.0, "bi": 0.8, "tri": 0.75}, {"en": "florida", "foreign": "\u0444\u043b\u043e\u0440\u0438\u0434\u0435", "rom": "floride", "score": 0.8976, "lev": 0.857, "jw": 0.943, "meta": 1.0, "sound": 1.0, "bi": 0.714, "tri": 0.667}, {"en": "brigade", "foreign": "\u0431\u0440\u0438\u0433\u0430\u0434\u044b", "rom": "brigady", "score": 0.8976, "lev": 0.857, "jw": 0.943, "meta": 1.0, "sound": 1.0, "bi": 0.714, "tri": 0.667}, {"en": "brigade", "foreign": "\u0431\u0440\u0438\u0433\u0430\u0434\u0430", "rom": "brigada", "score": 0.8976, "lev": 0.857, "jw": 0.943, "meta": 1.0, "sound": 1.0, "bi": 0.714, "tri": 0.667}, {"en": "formula", "foreign": "\u0444\u043e\u0440\u043c\u0443\u043b\u044b", "rom": "formuly", "score": 0.8976, "lev": 0.857, "jw": 0.943, "meta": 1.0, "sound": 1.0, "bi": 0.714, "tri": 0.667}, {"en": "ukraine", "foreign": "\u0443\u043a\u0440\u0430\u0438\u043d\u0430", "rom": "ukraina", "score": 0.8976, "lev": 0.857, "jw": 0.943, "meta": 1.0, "sound": 1.0, "bi": 0.714, "tri": 0.667}, {"en": "ukraine", "foreign": "\u0443\u043a\u0440\u0430\u0438\u043d\u0443", "rom": "ukrainu", "score": 0.8976, "lev": 0.857, "jw": 0.943, "meta": 1.0, "sound": 1.0, "bi": 0.714, "tri": 0.667}, {"en": "atlanta", "foreign": "\u0430\u0442\u043b\u0430\u043d\u0442\u0435", "rom": "atlante", "score": 0.8976, "lev": 0.857, "jw": 0.943, "meta": 1.0, "sound": 1.0, "bi": 0.714, "tri": 0.667}, {"en": "kennedy", "foreign": "\u043a\u0435\u043d\u043d\u0435\u0434\u0438", "rom": "kennedi", "score": 0.8976, "lev": 0.857, "jw": 0.943, "meta": 1.0, "sound": 1.0, "bi": 0.714, "tri": 0.667}, {"en": "alberta", "foreign": "\u0430\u043b\u044c\u0431\u0435\u0440\u0442\u044b", "rom": "alberty", "score": 0.8976, "lev": 0.857, "jw": 0.943, "meta": 1.0, "sound": 1.0, "bi": 0.714, "tri": 0.667}, {"en": "nigeria", "foreign": "\u043d\u0438\u0433\u0435\u0440\u0438\u0438", "rom": "nigerii", "score": 0.8976, "lev": 0.857, "jw": 0.943, "meta": 1.0, "sound": 1.0, "bi": 0.714, "tri": 0.667}, {"en": "gregory", "foreign": "\u0433\u0440\u0435\u0433\u043e\u0440\u0438", "rom": "gregori", "score": 0.8976, "lev": 0.857, "jw": 0.943, "meta": 1.0, "sound": 1.0, "bi": 0.714, "tri": 0.667}, {"en": "plastic", "foreign": "\u043f\u043b\u0430\u0441\u0442\u0438\u043a", "rom": "plastik", "score": 0.8976, "lev": 0.857, "jw": 0.943, "meta": 1.0, "sound": 1.0, "bi": 0.714, "tri": 0.667}, {"en": "melbourne", "foreign": "\u043c\u0435\u043b\u044c\u0431\u0443\u0440\u043d\u0435", "rom": "melburne", "score": 0.8944, "lev": 0.889, "jw": 0.978, "meta": 1.0, "sound": 1.0, "bi": 0.667, "tri": 0.444}, {"en": "sheffield", "foreign": "\u0448\u0435\u0444\u0444\u0438\u043b\u0434", "rom": "sheffild", "score": 0.8944, "lev": 0.889, "jw": 0.978, "meta": 1.0, "sound": 1.0, "bi": 0.667, "tri": 0.444}, {"en": "terrorism", "foreign": "\u0442\u0435\u0440\u0440\u043e\u0440\u0438\u0437\u043c", "rom": "terrorizm", "score": 0.8933, "lev": 0.889, "jw": 0.956, "meta": 1.0, "sound": 1.0, "bi": 0.6, "tri": 0.556}, {"en": "prefecture", "foreign": "\u043f\u0440\u0435\u0444\u0435\u043a\u0442\u0443\u0440\u0435", "rom": "prefekture", "score": 0.8927, "lev": 0.9, "jw": 0.96, "meta": 1.0, "sound": 1.0, "bi": 0.6, "tri": 0.455}, {"en": "minister", "foreign": "\u043c\u0438\u043d\u0438\u0441\u0442\u0440", "rom": "ministr", "score": 0.8911, "lev": 0.875, "jw": 0.975, "meta": 1.0, "sound": 1.0, "bi": 0.625, "tri": 0.571}], "bottom": [{"en": "west", "foreign": "\u0437\u0430\u043f\u0430\u0434\u043d\u0430\u044f", "rom": "zapadnaia", "score": 0.0222, "lev": 0.0, "jw": 0.0, "meta": 0.0, "sound": 0.0, "bi": 0.0, "tri": 0.0}, {"en": "free", "foreign": "\u0441\u0432\u043e\u0431\u043e\u0434\u043d\u044b\u0439", "rom": "svobodnyi", "score": 0.0222, "lev": 0.0, "jw": 0.0, "meta": 0.0, "sound": 0.0, "bi": 0.0, "tri": 0.0}, {"en": "free", "foreign": "\u0441\u0432\u043e\u0431\u043e\u0434\u043d\u043e\u0439", "rom": "svobodnoi", "score": 0.0222, "lev": 0.0, "jw": 0.0, "meta": 0.0, "sound": 0.0, "bi": 0.0, "tri": 0.0}, {"en": "girl", "foreign": "\u0434\u0435\u0432\u0447\u043e\u043d\u043a\u0430", "rom": "devchonka", "score": 0.0222, "lev": 0.0, "jw": 0.0, "meta": 0.0, "sound": 0.0, "bi": 0.0, "tri": 0.0}, {"en": "told", "foreign": "\u0440\u0430\u0441\u0441\u043a\u0430\u0437\u0430\u043b", "rom": "rasskazal", "score": 0.0222, "lev": 0.0, "jw": 0.0, "meta": 0.0, "sound": 0.0, "bi": 0.0, "tri": 0.0}, {"en": "tell", "foreign": "\u0440\u0430\u0441\u0441\u043a\u0430\u0437\u0430\u0442\u044c", "rom": "rasskazat", "score": 0.0222, "lev": 0.0, "jw": 0.0, "meta": 0.0, "sound": 0.0, "bi": 0.0, "tri": 0.0}, {"en": "boys", "foreign": "\u043c\u0430\u043b\u044c\u0447\u0438\u043a\u043e\u0432", "rom": "malchikov", "score": 0.0222, "lev": 0.0, "jw": 0.0, "meta": 0.0, "sound": 0.0, "bi": 0.0, "tri": 0.0}, {"en": "deep", "foreign": "\u0433\u043b\u0443\u0431\u043e\u043a\u0443\u044e", "rom": "glubokuiu", "score": 0.0222, "lev": 0.0, "jw": 0.0, "meta": 0.0, "sound": 0.0, "bi": 0.0, "tri": 0.0}, {"en": "deep", "foreign": "\u0433\u043b\u0443\u0431\u043e\u043a\u0430\u044f", "rom": "glubokaia", "score": 0.0222, "lev": 0.0, "jw": 0.0, "meta": 0.0, "sound": 0.0, "bi": 0.0, "tri": 0.0}, {"en": "any", "foreign": "\u043b\u044e\u0431\u0443\u044e", "rom": "liubuiu", "score": 0.0214, "lev": 0.0, "jw": 0.0, "meta": 0.0, "sound": 0.0, "bi": 0.0, "tri": 0.0}, {"en": "now", "foreign": "\u0441\u0435\u0439\u0447\u0430\u0441", "rom": "seichas", "score": 0.0214, "lev": 0.0, "jw": 0.0, "meta": 0.0, "sound": 0.0, "bi": 0.0, "tri": 0.0}, {"en": "won", "foreign": "\u0432\u044b\u0438\u0433\u0440\u0430\u043b", "rom": "vyigral", "score": 0.0214, "lev": 0.0, "jw": 0.0, "meta": 0.0, "sound": 0.0, "bi": 0.0, "tri": 0.0}, {"en": "old", "foreign": "\u0441\u0442\u0430\u0440\u0430\u044f", "rom": "staraia", "score": 0.0214, "lev": 0.0, "jw": 0.0, "meta": 0.0, "sound": 0.0, "bi": 0.0, "tri": 0.0}, {"en": "top", "foreign": "\u0441\u0432\u0435\u0440\u0445\u0443", "rom": "sverkhu", "score": 0.0214, "lev": 0.0, "jw": 0.0, "meta": 0.0, "sound": 0.0, "bi": 0.0, "tri": 0.0}, {"en": "air", "foreign": "\u0432\u043e\u0437\u0434\u0443\u0445", "rom": "vozdukh", "score": 0.0214, "lev": 0.0, "jw": 0.0, "meta": 0.0, "sound": 0.0, "bi": 0.0, "tri": 0.0}, {"en": "without", "foreign": "\u0431\u0435\u0437", "rom": "bez", "score": 0.0214, "lev": 0.0, "jw": 0.0, "meta": 0.0, "sound": 0.0, "bi": 0.0, "tri": 0.0}, {"en": "low", "foreign": "\u043d\u0438\u0437\u043a\u0430\u044f", "rom": "nizkaia", "score": 0.0214, "lev": 0.0, "jw": 0.0, "meta": 0.0, "sound": 0.0, "bi": 0.0, "tri": 0.0}, {"en": "saw", "foreign": "\u0443\u0432\u0438\u0434\u0435\u043b\u0430", "rom": "uvidela", "score": 0.0214, "lev": 0.0, "jw": 0.0, "meta": 0.0, "sound": 0.0, "bi": 0.0, "tri": 0.0}, {"en": "bad", "foreign": "\u043f\u043b\u043e\u0445\u043e\u0439", "rom": "plokhoi", "score": 0.0214, "lev": 0.0, "jw": 0.0, "meta": 0.0, "sound": 0.0, "bi": 0.0, "tri": 0.0}, {"en": "log", "foreign": "\u0436\u0443\u0440\u043d\u0430\u043b", "rom": "zhurnal", "score": 0.0214, "lev": 0.0, "jw": 0.0, "meta": 0.0, "sound": 0.0, "bi": 0.0, "tri": 0.0}, {"en": "boy", "foreign": "\u043c\u0430\u043b\u044c\u0447\u0438\u043a", "rom": "malchik", "score": 0.0214, "lev": 0.0, "jw": 0.0, "meta": 0.0, "sound": 0.0, "bi": 0.0, "tri": 0.0}, {"en": "hundred", "foreign": "\u0441\u0442\u043e", "rom": "sto", "score": 0.0214, "lev": 0.0, "jw": 0.0, "meta": 0.0, "sound": 0.0, "bi": 0.0, "tri": 0.0}, {"en": "dam", "foreign": "\u043f\u043b\u043e\u0442\u0438\u043d\u044b", "rom": "plotiny", "score": 0.0214, "lev": 0.0, "jw": 0.0, "meta": 0.0, "sound": 0.0, "bi": 0.0, "tri": 0.0}, {"en": "singing", "foreign": "\u043f\u0435\u0442\u044c", "rom": "pet", "score": 0.0214, "lev": 0.0, "jw": 0.0, "meta": 0.0, "sound": 0.0, "bi": 0.0, "tri": 0.0}, {"en": "dry", "foreign": "\u0441\u0443\u0445\u0430\u044f", "rom": "sukhaia", "score": 0.0214, "lev": 0.0, "jw": 0.0, "meta": 0.0, "sound": 0.0, "bi": 0.0, "tri": 0.0}, {"en": "fun", "foreign": "\u0432\u0435\u0441\u0435\u043b\u044b\u0435", "rom": "veselye", "score": 0.0214, "lev": 0.0, "jw": 0.0, "meta": 0.0, "sound": 0.0, "bi": 0.0, "tri": 0.0}, {"en": "odd", "foreign": "\u0441\u0442\u0440\u0430\u043d\u043d\u043e", "rom": "stranno", "score": 0.0214, "lev": 0.0, "jw": 0.0, "meta": 0.0, "sound": 0.0, "bi": 0.0, "tri": 0.0}, {"en": "tribute", "foreign": "\u0434\u0430\u043d\u044c", "rom": "dan", "score": 0.0214, "lev": 0.0, "jw": 0.0, "meta": 0.0, "sound": 0.0, "bi": 0.0, "tri": 0.0}, {"en": "bed", "foreign": "\u043a\u0440\u043e\u0432\u0430\u0442\u0438", "rom": "krovati", "score": 0.0214, "lev": 0.0, "jw": 0.0, "meta": 0.0, "sound": 0.0, "bi": 0.0, "tri": 0.0}, {"en": "civil", "foreign": "\u0433\u0440\u0430\u0436\u0434\u0430\u043d\u0441\u043a\u043e\u0435", "rom": "grazhdanskoe", "score": 0.0208, "lev": 0.0, "jw": 0.0, "meta": 0.0, "sound": 0.0, "bi": 0.0, "tri": 0.0}, {"en": "contribution", "foreign": "\u0432\u043a\u043b\u0430\u0434", "rom": "vklad", "score": 0.0208, "lev": 0.0, "jw": 0.0, "meta": 0.0, "sound": 0.0, "bi": 0.0, "tri": 0.0}, {"en": "hello", "foreign": "\u0437\u0434\u0440\u0430\u0432\u0441\u0442\u0432\u0443\u0439\u0442\u0435", "rom": "zdravstvuite", "score": 0.0208, "lev": 0.0, "jw": 0.0, "meta": 0.0, "sound": 0.0, "bi": 0.0, "tri": 0.0}, {"en": "would", "foreign": "\u0431\u044b", "rom": "by", "score": 0.02, "lev": 0.0, "jw": 0.0, "meta": 0.0, "sound": 0.0, "bi": 0.0, "tri": 0.0}, {"en": "until", "foreign": "\u0434\u043e", "rom": "do", "score": 0.02, "lev": 0.0, "jw": 0.0, "meta": 0.0, "sound": 0.0, "bi": 0.0, "tri": 0.0}, {"en": "feel", "foreign": "\u0447\u0443\u0432\u0441\u0442\u0432\u0443\u044e", "rom": "chuvstvuiu", "score": 0.02, "lev": 0.0, "jw": 0.0, "meta": 0.0, "sound": 0.0, "bi": 0.0, "tri": 0.0}, {"en": "lack", "foreign": "\u043e\u0442\u0441\u0443\u0442\u0441\u0442\u0432\u0438\u0435", "rom": "otsutstvie", "score": 0.02, "lev": 0.0, "jw": 0.0, "meta": 0.0, "sound": 0.0, "bi": 0.0, "tri": 0.0}, {"en": "wins", "foreign": "\u043f\u043e\u0431\u0435\u0436\u0434\u0430\u0435\u0442", "rom": "pobezhdaet", "score": 0.02, "lev": 0.0, "jw": 0.0, "meta": 0.0, "sound": 0.0, "bi": 0.0, "tri": 0.0}, {"en": "civil", "foreign": "\u0433\u0440\u0430\u0436\u0434\u0430\u043d\u0441\u043a\u043e\u0433\u043e", "rom": "grazhdanskogo", "score": 0.0192, "lev": 0.0, "jw": 0.0, "meta": 0.0, "sound": 0.0, "bi": 0.0, "tri": 0.0}, {"en": "contributions", "foreign": "\u0432\u043a\u043b\u0430\u0434", "rom": "vklad", "score": 0.0192, "lev": 0.0, "jw": 0.0, "meta": 0.0, "sound": 0.0, "bi": 0.0, "tri": 0.0}, {"en": "won", "foreign": "\u0432\u044b\u0438\u0433\u0440\u0430\u043b\u0430", "rom": "vyigrala", "score": 0.0188, "lev": 0.0, "jw": 0.0, "meta": 0.0, "sound": 0.0, "bi": 0.0, "tri": 0.0}, {"en": "man", "foreign": "\u0447\u0435\u043b\u043e\u0432\u0435\u043a", "rom": "chelovek", "score": 0.0188, "lev": 0.0, "jw": 0.0, "meta": 0.0, "sound": 0.0, "bi": 0.0, "tri": 0.0}, {"en": "box", "foreign": "\u044f\u0449\u0438\u043a", "rom": "iashchik", "score": 0.0188, "lev": 0.0, "jw": 0.0, "meta": 0.0, "sound": 0.0, "bi": 0.0, "tri": 0.0}, {"en": "gun", "foreign": "\u043f\u0438\u0441\u0442\u043e\u043b\u0435\u0442", "rom": "pistolet", "score": 0.0188, "lev": 0.0, "jw": 0.0, "meta": 0.0, "sound": 0.0, "bi": 0.0, "tri": 0.0}, {"en": "feel", "foreign": "\u0447\u0443\u0432\u0441\u0442\u0432\u043e\u0432\u0430\u0442\u044c", "rom": "chuvstvovat", "score": 0.0182, "lev": 0.0, "jw": 0.0, "meta": 0.0, "sound": 0.0, "bi": 0.0, "tri": 0.0}, {"en": "holy", "foreign": "\u0441\u0432\u044f\u0442\u0435\u0439\u0448\u0438\u0439", "rom": "sviateishii", "score": 0.0182, "lev": 0.0, "jw": 0.0, "meta": 0.0, "sound": 0.0, "bi": 0.0, "tri": 0.0}, {"en": "duty", "foreign": "\u043e\u0431\u044f\u0437\u0430\u043d\u043d\u043e\u0441\u0442\u044c", "rom": "obiazannost", "score": 0.0182, "lev": 0.0, "jw": 0.0, "meta": 0.0, "sound": 0.0, "bi": 0.0, "tri": 0.0}, {"en": "and", "foreign": "\u0438", "rom": "i", "score": 0.0167, "lev": 0.0, "jw": 0.0, "meta": 0.0, "sound": 0.0, "bi": 0.0, "tri": 0.0}, {"en": "bill", "foreign": "\u0437\u0430\u043a\u043e\u043d\u043e\u043f\u0440\u043e\u0435\u043a\u0442", "rom": "zakonoproekt", "score": 0.0167, "lev": 0.0, "jw": 0.0, "meta": 0.0, "sound": 0.0, "bi": 0.0, "tri": 0.0}, {"en": "box", "foreign": "\u0448\u043a\u0430\u0442\u0443\u043b\u043a\u0430", "rom": "shkatulka", "score": 0.0167, "lev": 0.0, "jw": 0.0, "meta": 0.0, "sound": 0.0, "bi": 0.0, "tri": 0.0}, {"en": "with", "foreign": "\u0441", "rom": "s", "score": 0.0125, "lev": 0.0, "jw": 0.0, "meta": 0.0, "sound": 0.0, "bi": 0.0, "tri": 0.0}], "all_count": 10000, "histogram": [743, 259, 460, 2061, 1890, 829, 406, 263, 281, 277, 252, 287, 300, 250, 161, 144, 168, 133, 82, 754]}